[{"topic":"land cover","top_0_similar_word":"large","top_1_similar_word":"small","top_2_similar_word":"entire","top_3_similar_word":"covered","top_4_similar_word":"except"},{"topic":"image classification","top_0_similar_word":"characteristics","top_1_similar_word":"model","top_2_similar_word":"color","top_3_similar_word":"forms","top_4_similar_word":"unique"},{"topic":"data weighting","top_0_similar_word":"measurement","top_1_similar_word":"indicator","top_2_similar_word":"component","top_3_similar_word":"tracking","top_4_similar_word":"calculated"},{"topic":"cover classification","top_0_similar_word":"types","top_1_similar_word":"standard","top_2_similar_word":"forms","top_3_similar_word":"categories","top_4_similar_word":"available"},{"topic":"optical data","top_0_similar_word":"measurement","top_1_similar_word":"digital","top_2_similar_word":"imaging","top_3_similar_word":"electronic","top_4_similar_word":"systems"},{"topic":"weighting method","top_0_similar_word":"calculation","top_1_similar_word":"measurement","top_2_similar_word":"calculating","top_3_similar_word":"calculations","top_4_similar_word":"calculated"},{"topic":"cover mapping","top_0_similar_word":"maps","top_1_similar_word":"data","top_2_similar_word":"material","top_3_similar_word":"search","top_4_similar_word":"using"},{"topic":"colour infrared","top_0_similar_word":"color","top_1_similar_word":"wavelengths","top_2_similar_word":"imagery","top_3_similar_word":"sensor","top_4_similar_word":"laser"},{"topic":"urban slum","top_0_similar_word":"slums","top_1_similar_word":"neighborhoods","top_2_similar_word":"dwellers","top_3_similar_word":"neighborhood","top_4_similar_word":"rural"},{"topic":"maximum likelihood","top_0_similar_word":"increases","top_1_similar_word":"minimum","top_2_similar_word":"limit","top_3_similar_word":"reduced","top_4_similar_word":"threshold"}]