[{"Cluster":0,"NumDocs":36,"DocIds":[11,35,69,72,84,144,166,171,173,176,183,196,197,221,286,308,314,328,339,341,393,417,430,431,438,444,456,461,462,472,473,550,553,569,578,587],"TopWords_chi":[{"collocation":"closely packed","score":7636.0,"doc_ids":[171]},{"collocation":"de janeiro","score":7636.0,"doc_ids":[166]},{"collocation":"mahoning county","score":7636.0,"doc_ids":[197]},{"collocation":"rights reserved","score":7636.0,"doc_ids":[328,393,569]},{"collocation":"rio de","score":7636.0,"doc_ids":[166]},{"collocation":"roof superstructures","score":7636.0,"doc_ids":[430]},{"collocation":"thermal comfort","score":6871.4989379835,"doc_ids":[286]},{"collocation":"random forest","score":6680.6241971425,"doc_ids":[72,171,221,430,431,462]},{"collocation":"machine learning","score":5909.8702540163,"doc_ids":[11,69,72,84,144,166,171,173,197,221,286,308,314,328,341,417,430,431,438,444,461,472,473,569,578,587]},{"collocation":"derelict sites","score":5726.2497052273,"doc_ids":[173]}],"TopWords_likelihood":[{"collocation":"machine learning","score":434.9213455949,"doc_ids":[11,69,72,84,144,166,171,173,197,221,286,308,314,328,341,417,430,431,438,444,461,472,473,569,578,587]},{"collocation":"land use","score":193.3915286066,"doc_ids":[72,84,166,431,456,472]},{"collocation":"thermal comfort","score":132.8690116494,"doc_ids":[286]},{"collocation":"closely packed","score":125.7706180107,"doc_ids":[171]},{"collocation":"support vector","score":119.3737550638,"doc_ids":[69,84,197,328,430,444]},{"collocation":"urban planning","score":112.5079043324,"doc_ids":[72,144,171,173,183,221,341,430,438,444,462,472,473,550,553,569,578]},{"collocation":"urban land","score":108.3774403869,"doc_ids":[84,431,456,472]},{"collocation":"point clouds","score":106.6491910791,"doc_ids":[144,171,430]},{"collocation":"random forest","score":105.891324987,"doc_ids":[72,171,221,430,431,462]},{"collocation":"shared bus","score":99.9910634611,"doc_ids":[461]}],"TopWords_pmi":[{"collocation":"de janeiro","score":11.3136388867,"doc_ids":[166]},{"collocation":"mahoning county","score":11.3136388867,"doc_ids":[197]},{"collocation":"rights reserved","score":11.3136388867,"doc_ids":[328,393,569]},{"collocation":"rio de","score":11.3136388867,"doc_ids":[166]},{"collocation":"roof superstructures","score":11.3136388867,"doc_ids":[430]},{"collocation":"derelict sites","score":10.8986013874,"doc_ids":[173]},{"collocation":"housing inequality","score":10.3136388867,"doc_ids":[438]},{"collocation":"neural network","score":9.9917107918,"doc_ids":[173,221,328]},{"collocation":"closely packed","score":9.8986013874,"doc_ids":[171]},{"collocation":"random forest","score":9.8986013874,"doc_ids":[72,171,221,430,431,462]}]},{"Cluster":1,"NumDocs":67,"DocIds":[0,2,18,19,20,36,40,53,55,57,60,63,70,80,98,99,104,109,110,124,136,143,147,155,170,177,185,210,219,222,236,237,241,248,250,255,262,291,326,363,366,377,384,388,400,410,427,429,436,437,443,449,450,453,454,459,464,468,485,503,504,505,530,534,537,567,574],"TopWords_chi":[{"collocation":"rights reserved","score":14892.0,"doc_ids":[136,363,377,574]},{"collocation":"remote sensing","score":12836.8300075367,"doc_ids":[2,20,53,70,99,109,147,222,237,437,450,485,504,505,537]},{"collocation":"random forest","score":12060.7188577256,"doc_ids":[53,55,143,291,400,443]},{"collocation":"fecal sludge","score":11168.2498488817,"doc_ids":[443]},{"collocation":"cellular automata","score":10422.2990124286,"doc_ids":[104,143,155,485]},{"collocation":"artificial intelligence","score":9924.6644268244,"doc_ids":[60,155,237,241,366,377,464,534]},{"collocation":"street view","score":9624.0790333554,"doc_ids":[410,427]},{"collocation":"deprivation pockets","score":9118.3734850067,"doc_ids":[110]},{"collocation":"turning movements","score":8933.9997582108,"doc_ids":[60]},{"collocation":"heat island","score":8375.2496641771,"doc_ids":[98,99,255]}],"TopWords_likelihood":[{"collocation":"machine learning","score":482.1199350588,"doc_ids":[18,19,40,55,60,70,80,104,109,110,124,147,170,177,185,210,219,222,236,248,255,262,291,326,384,388,400,410,427,429,437,450,454,485,503,504,530,534,567]},{"collocation":"remote sensing","score":353.3605411742,"doc_ids":[2,20,53,70,99,109,147,222,237,437,450,485,504,505,537]},{"collocation":"land use","score":260.8531498919,"doc_ids":[19,36,70,104,143,177,237,427,437,505,537]},{"collocation":"urban planning","score":249.6493671916,"doc_ids":[19,20,40,53,57,60,63,70,98,104,110,143,185,219,237,248,255,363,366,384,429,437,450,454,459,464,485,503,504,505,530,534]},{"collocation":"deep learning","score":227.5978252017,"doc_ids":[99,210,219,237,326,366,384,436,437,450,454,505,530,534]},{"collocation":"electric consumption","score":174.3323060891,"doc_ids":[326]},{"collocation":"neural network","score":167.9170577033,"doc_ids":[99,104,110,143,155,210,400,436,505,534]},{"collocation":"convolutional neural","score":160.98815984,"doc_ids":[19,99,104,110,143,210,436,505]},{"collocation":"support vector","score":147.5893280259,"doc_ids":[2,53,63,80,109,136,143,291,400,450]},{"collocation":"artificial intelligence","score":147.0177452728,"doc_ids":[60,155,237,241,366,377,464,534]}],"TopWords_pmi":[{"collocation":"fecal sludge","score":11.8622499009,"doc_ids":[443]},{"collocation":"rights reserved","score":11.8622499009,"doc_ids":[136,363,377,574]},{"collocation":"turning movements","score":11.540321806,"doc_ids":[60]},{"collocation":"heat island","score":11.4472124016,"doc_ids":[98,99,255]},{"collocation":"perennial drainage","score":11.4472124016,"doc_ids":[503]},{"collocation":"ground truth","score":11.2772874001,"doc_ids":[18,19]},{"collocation":"earth observation","score":11.1252843067,"doc_ids":[459,504]},{"collocation":"hydrologic modelling","score":11.1252843067,"doc_ids":[147]},{"collocation":"query engine","score":10.8622499009,"doc_ids":[384]},{"collocation":"cellular automata","score":10.540321806,"doc_ids":[104,143,155,485]}]},{"Cluster":2,"NumDocs":57,"DocIds":[17,37,56,59,105,107,115,121,122,132,140,157,160,188,204,206,209,214,224,235,239,242,261,271,272,287,294,297,298,300,301,306,310,320,334,338,350,351,352,380,387,397,399,407,460,463,476,482,489,497,507,542,543,560,590,596,599],"TopWords_chi":[{"collocation":"commons attribution","score":12002.0,"doc_ids":[107,287,507]},{"collocation":"heat islands","score":12002.0,"doc_ids":[206]},{"collocation":"pen net","score":12002.0,"doc_ids":[105]},{"collocation":"rights reserved","score":12002.0,"doc_ids":[271,320,463]},{"collocation":"unreinforced masonry","score":12002.0,"doc_ids":[460]},{"collocation":"carbon sequestration","score":10667.5549626665,"doc_ids":[560]},{"collocation":"food productivity","score":10500.8744893706,"doc_ids":[560]},{"collocation":"positive deviance","score":9999.9986101846,"doc_ids":[188]},{"collocation":"creative commons","score":9000.7498124844,"doc_ids":[107,287,507]},{"collocation":"earth engine","score":9000.7498124844,"doc_ids":[204]}],"TopWords_likelihood":[{"collocation":"machine learning","score":501.3029411428,"doc_ids":[37,56,59,105,115,121,140,160,204,206,209,214,224,235,242,261,271,272,287,298,300,301,310,334,350,351,352,380,387,399,463,476,497,542,560,590]},{"collocation":"land use","score":242.7894037709,"doc_ids":[17,160,224,271,294,297,300,334,407,497,507]},{"collocation":"positive deviance","score":150.9830664986,"doc_ids":[188]},{"collocation":"random forest","score":144.9386072008,"doc_ids":[59,204,206,209,214,224,310,350,497]},{"collocation":"urban planning","score":140.4655157776,"doc_ids":[37,105,107,115,121,132,140,157,188,206,271,287,297,300,301,306,334,338,350,351,463,497,507,560,599]},{"collocation":"land cover","score":137.7158169133,"doc_ids":[224,300,407]},{"collocation":"neural network","score":128.535628959,"doc_ids":[37,105,209,235,242,298,380,460]},{"collocation":"carbon sequestration","score":126.729881283,"doc_ids":[560]},{"collocation":"heat islands","score":118.2527746081,"doc_ids":[206]},{"collocation":"remote sensing","score":113.8394240138,"doc_ids":[17,37,105,140,188,497]}],"TopWords_pmi":[{"collocation":"commons attribution","score":11.9660247138,"doc_ids":[107,287,507]},{"collocation":"rights reserved","score":11.9660247138,"doc_ids":[271,320,463]},{"collocation":"creative commons","score":11.5509872145,"doc_ids":[107,287,507]},{"collocation":"earth engine","score":11.5509872145,"doc_ids":[204]},{"collocation":"unreinforced masonry","score":11.5509872145,"doc_ids":[460]},{"collocation":"normalized difference","score":11.2290591196,"doc_ids":[242]},{"collocation":"open access","score":11.1359497152,"doc_ids":[107,287,507]},{"collocation":"pen net","score":10.9660247138,"doc_ids":[105]},{"collocation":"heat islands","score":10.7436322925,"doc_ids":[206]},{"collocation":"google earth","score":10.7436322925,"doc_ids":[204]}]},{"Cluster":3,"NumDocs":21,"DocIds":[5,34,66,119,120,127,129,153,167,220,225,228,246,303,324,379,395,442,474,523,597],"TopWords_chi":[{"collocation":"random forest","score":4625.0,"doc_ids":[228,324]},{"collocation":"red mason","score":4625.0,"doc_ids":[66]},{"collocation":"smart card","score":4625.0,"doc_ids":[303]},{"collocation":"sun exposure","score":4625.0,"doc_ids":[66]},{"collocation":"sediment yield","score":4110.2206820206,"doc_ids":[5]},{"collocation":"soil erosion","score":4110.2206820206,"doc_ids":[5]},{"collocation":"color icons","score":3699.1993075092,"doc_ids":[379]},{"collocation":"temporally varying","score":3699.1993075092,"doc_ids":[442]},{"collocation":"remote sensing","score":3539.2628096941,"doc_ids":[5,220,228,324]},{"collocation":"architectural color","score":2958.3984850827,"doc_ids":[379]}],"TopWords_likelihood":[{"collocation":"machine learning","score":153.8764519882,"doc_ids":[66,120,153,228,246,303,324,442,474]},{"collocation":"urban planning","score":146.3258677617,"doc_ids":[120,129,153,167,220,225,228,246,324,442,474,523]},{"collocation":"sediment yield","score":111.4638181838,"doc_ids":[5]},{"collocation":"soil erosion","score":111.4638181838,"doc_ids":[5]},{"collocation":"remote sensing","score":92.8396890903,"doc_ids":[5,220,228,324]},{"collocation":"land use","score":80.5782486083,"doc_ids":[324]},{"collocation":"big data","score":73.7953316527,"doc_ids":[129,225,324]},{"collocation":"land cover","score":68.0629947331,"doc_ids":[5]},{"collocation":"ai technologies","score":67.6106466818,"doc_ids":[34,129]},{"collocation":"random forest","score":64.4200378534,"doc_ids":[228,324]}],"TopWords_pmi":[{"collocation":"red mason","score":10.5902751496,"doc_ids":[66]},{"collocation":"smart card","score":10.5902751496,"doc_ids":[303]},{"collocation":"sun exposure","score":10.5902751496,"doc_ids":[66]},{"collocation":"random forest","score":10.1752376503,"doc_ids":[228,324]},{"collocation":"color icons","score":9.8533095554,"doc_ids":[379]},{"collocation":"temporally varying","score":9.8533095554,"doc_ids":[442]},{"collocation":"varying impacts","score":9.8533095554,"doc_ids":[442]},{"collocation":"artificial intelligence","score":9.5902751496,"doc_ids":[34,129]},{"collocation":"mason bee","score":9.5902751496,"doc_ids":[66]},{"collocation":"architectural color","score":9.5313814605,"doc_ids":[379]}]},{"Cluster":4,"NumDocs":57,"DocIds":[1,4,9,16,24,25,29,30,48,52,62,67,71,75,76,83,89,101,108,111,112,125,138,146,149,165,175,181,203,223,227,233,244,296,299,312,323,331,344,346,360,381,406,458,470,471,480,487,496,502,520,531,536,538,539,547,563],"TopWords_chi":[{"collocation":"aperture radar","score":12446.0,"doc_ids":[25,71,538]},{"collocation":"rights reserved","score":12446.0,"doc_ids":[175,296,547]},{"collocation":"computer vision","score":10667.1424437299,"doc_ids":[125,360,470,536]},{"collocation":"remote sensing","score":10666.2840598359,"doc_ids":[52,71,111,138,203,471,538,539]},{"collocation":"cellular automata","score":10370.8329984192,"doc_ids":[9,29,75]},{"collocation":"solar radiation","score":9955.9997428066,"doc_ids":[146,149]},{"collocation":"synthetic aperture","score":9333.7498191754,"doc_ids":[25,71,538]},{"collocation":"transition rules","score":9333.7498191754,"doc_ids":[9,29]},{"collocation":"machine learning","score":8407.7273356765,"doc_ids":[16,25,29,30,52,62,67,75,76,83,89,101,108,111,112,125,138,149,175,181,223,227,233,323,331,344,346,360,381,458,470,471,480,487,496,520,531,538,539,563]},{"collocation":"random forest","score":8328.344534341,"doc_ids":[25,30,67,89,111,112,323,539]}],"TopWords_likelihood":[{"collocation":"machine learning","score":649.1407607058,"doc_ids":[16,25,29,30,52,62,67,75,76,83,89,101,108,111,112,125,138,149,175,181,223,227,233,323,331,344,346,360,381,458,470,471,480,487,496,520,531,538,539,563]},{"collocation":"urban planning","score":222.7181667201,"doc_ids":[29,48,67,71,76,101,108,111,112,138,165,175,203,223,296,299,312,331,344,360,458,470,471,496,520,531,536,538,539,547]},{"collocation":"artificial intelligence","score":192.3801256219,"doc_ids":[4,48,71,138,244,312,487,502]},{"collocation":"land cover","score":182.302583538,"doc_ids":[25,30,471,531,539]},{"collocation":"remote sensing","score":179.1671193535,"doc_ids":[52,71,111,138,203,471,538,539]},{"collocation":"big data","score":170.3583531491,"doc_ids":[4,16,52,71,138,227,323,344,458,487,502]},{"collocation":"change detection","score":140.5774255671,"doc_ids":[71]},{"collocation":"land use","score":134.1439037865,"doc_ids":[76,112,203,244,471,539]},{"collocation":"random forest","score":127.3067436668,"doc_ids":[25,30,67,89,111,112,323,539]},{"collocation":"computer vision","score":97.9042197343,"doc_ids":[125,360,470,536]}],"TopWords_pmi":[{"collocation":"aperture radar","score":12.0184320302,"doc_ids":[25,71,538]},{"collocation":"rights reserved","score":12.0184320302,"doc_ids":[175,296,547]},{"collocation":"synthetic aperture","score":11.6033945309,"doc_ids":[25,71,538]},{"collocation":"transition rules","score":11.6033945309,"doc_ids":[9,29]},{"collocation":"commuting flows","score":11.281466436,"doc_ids":[296]},{"collocation":"dimensionality reduction","score":11.281466436,"doc_ids":[381]},{"collocation":"gradient boosting","score":11.281466436,"doc_ids":[83,296]},{"collocation":"solar radiation","score":11.281466436,"doc_ids":[146,149]},{"collocation":"cellular automata","score":11.0184320302,"doc_ids":[9,29,75]},{"collocation":"computer vision","score":10.7960396088,"doc_ids":[125,360,470,536]}]},{"Cluster":5,"NumDocs":45,"DocIds":[47,145,148,182,191,195,215,217,258,267,273,274,281,315,316,317,318,321,337,342,353,356,375,385,390,394,401,405,411,465,479,501,508,522,554,555,557,568,581,583,588,591,592,595,598],"TopWords_chi":[{"collocation":"remote sensing","score":8621.0,"doc_ids":[182,342,401,568]},{"collocation":"random forest","score":6895.9996286411,"doc_ids":[353,390,401,479]},{"collocation":"cooling loads","score":6464.9997389185,"doc_ids":[479]},{"collocation":"layout synthesis","score":6464.9997389185,"doc_ids":[316]},{"collocation":"machine learning","score":6211.6796967063,"doc_ids":[47,145,182,195,215,217,258,267,281,315,342,353,356,375,390,394,401,405,411,465,479,508,522,554,557,568,581,583,591]},{"collocation":"greater athens","score":5745.9993810684,"doc_ids":[182]},{"collocation":"mediterranean climate","score":5171.3995822697,"doc_ids":[479]},{"collocation":"rbg melbourne","score":5171.3995822697,"doc_ids":[598]},{"collocation":"community deprivation","score":4847.8119198055,"doc_ids":[145]},{"collocation":"park accessibility","score":4529.5658236988,"doc_ids":[145]}],"TopWords_likelihood":[{"collocation":"machine learning","score":422.7034956959,"doc_ids":[47,145,182,195,215,217,258,267,281,315,342,353,356,375,390,394,401,405,411,465,479,508,522,554,557,568,581,583,591]},{"collocation":"urban planning","score":171.7088314053,"doc_ids":[145,148,191,258,274,315,316,318,337,342,353,375,385,394,401,405,501,522,557,583,595]},{"collocation":"smart cities","score":136.0726230846,"doc_ids":[47,337,405,501,581]},{"collocation":"land use","score":114.7997994004,"doc_ids":[274,522,595]},{"collocation":"park accessibility","score":112.8778479518,"doc_ids":[145]},{"collocation":"semantic segmentation","score":109.1979067238,"doc_ids":[148,568]},{"collocation":"remote sensing","score":99.238185945,"doc_ids":[182,342,401,568]},{"collocation":"vehicle ownership","score":94.2108406501,"doc_ids":[353]},{"collocation":"artificial intelligence","score":93.3206204002,"doc_ids":[318,321,337,501,522,555,583,595]},{"collocation":"air quality","score":69.075446311,"doc_ids":[273]}],"TopWords_pmi":[{"collocation":"cooling loads","score":11.0736395103,"doc_ids":[479]},{"collocation":"layout synthesis","score":11.0736395103,"doc_ids":[316]},{"collocation":"mediterranean climate","score":10.7517114154,"doc_ids":[479]},{"collocation":"random forest","score":10.7517114154,"doc_ids":[353,390,401,479]},{"collocation":"rbg melbourne","score":10.7517114154,"doc_ids":[598]},{"collocation":"community deprivation","score":10.658602011,"doc_ids":[145]},{"collocation":"greater athens","score":10.4886770096,"doc_ids":[182]},{"collocation":"remote sensing","score":10.4886770096,"doc_ids":[182,342,401,568]},{"collocation":"explanatory variables","score":9.7517114154,"doc_ids":[356]},{"collocation":"landsat imagery","score":9.658602011,"doc_ids":[182,568]}]},{"Cluster":6,"NumDocs":30,"DocIds":[7,21,51,82,85,118,137,168,184,200,208,252,253,322,325,347,412,415,419,424,434,439,445,451,466,483,525,526,570,572],"TopWords_chi":[{"collocation":"lagos metropolis","score":7338.0,"doc_ids":[466]},{"collocation":"remote sensing","score":7338.0,"doc_ids":[21,424,451]},{"collocation":"carbon emissions","score":6113.331058952,"doc_ids":[85,253]},{"collocation":"physical assets","score":5502.7496932515,"doc_ids":[253]},{"collocation":"artificial intelligence","score":4584.3737215328,"doc_ids":[7,200,322,466]},{"collocation":"random forest","score":4401.5995092025,"doc_ids":[347,451,526]},{"collocation":"air quality","score":3987.8066793758,"doc_ids":[415,525,526]},{"collocation":"machine learning","score":3723.7075495111,"doc_ids":[21,51,82,85,168,208,252,253,412,415,424,439,445,451,570,572]},{"collocation":"feature parameters","score":3667.4993865031,"doc_ids":[412]},{"collocation":"localization decisions","score":3667.4993865031,"doc_ids":[570]}],"TopWords_likelihood":[{"collocation":"machine learning","score":244.0028949929,"doc_ids":[21,51,82,85,168,208,252,253,412,415,424,439,445,451,570,572]},{"collocation":"air quality","score":159.8052354555,"doc_ids":[415,525,526]},{"collocation":"carbon emissions","score":141.1376273395,"doc_ids":[85,253]},{"collocation":"neural network","score":139.0672399143,"doc_ids":[253,412,434,572]},{"collocation":"urban planning","score":129.9276384404,"doc_ids":[21,51,85,118,137,168,184,200,208,253,325,347,424,439,445,451,483,525,526,572]},{"collocation":"landslide susceptibility","score":93.5248061186,"doc_ids":[168,325]},{"collocation":"results show","score":89.1383124026,"doc_ids":[21,51,85,118,184,451,570,572]},{"collocation":"urban areas","score":83.3663983366,"doc_ids":[21,184,419,434,483,525,526]},{"collocation":"transit mobility","score":74.5688755288,"doc_ids":[419]},{"collocation":"artificial intelligence","score":72.3254174173,"doc_ids":[7,200,322,466]}],"TopWords_pmi":[{"collocation":"lagos metropolis","score":11.2562086885,"doc_ids":[466]},{"collocation":"remote sensing","score":11.2562086885,"doc_ids":[21,424,451]},{"collocation":"physical assets","score":10.8411711892,"doc_ids":[253]},{"collocation":"random forest","score":10.5192430944,"doc_ids":[347,451,526]},{"collocation":"feature parameters","score":10.2562086885,"doc_ids":[412]},{"collocation":"localization decisions","score":10.2562086885,"doc_ids":[570]},{"collocation":"path dependency","score":10.2562086885,"doc_ids":[570]},{"collocation":"cfd simulation","score":9.8411711892,"doc_ids":[572]},{"collocation":"artificial intelligence","score":9.8411711892,"doc_ids":[7,200,322,466]},{"collocation":"help predict","score":9.7822775002,"doc_ids":[572]}]},{"Cluster":7,"NumDocs":55,"DocIds":[10,13,14,15,26,42,58,61,65,68,78,87,90,92,114,134,135,180,193,194,211,216,238,245,268,270,313,330,345,359,362,364,365,374,378,383,389,409,421,422,426,435,440,469,475,491,506,512,516,517,535,541,545,552,556],"TopWords_chi":[{"collocation":"crime count","score":12092.0,"doc_ids":[374]},{"collocation":"dar es","score":12092.0,"doc_ids":[238]},{"collocation":"es salaam","score":12092.0,"doc_ids":[238]},{"collocation":"geographically weighted","score":12092.0,"doc_ids":[10,345]},{"collocation":"remote sensing","score":12092.0,"doc_ids":[90,245,313,364,365,378,389,469]},{"collocation":"rights reserved","score":12092.0,"doc_ids":[78,359,378]},{"collocation":"upper awash","score":12092.0,"doc_ids":[90]},{"collocation":"carbon emissions","score":8059.9995587911,"doc_ids":[440]},{"collocation":"path loss","score":8059.9995587911,"doc_ids":[362]},{"collocation":"surface temperature","score":7737.2794208996,"doc_ids":[330,421]}],"TopWords_likelihood":[{"collocation":"machine learning","score":497.2946848615,"doc_ids":[13,14,15,26,65,68,87,92,114,134,180,193,194,211,216,245,313,330,359,378,383,389,421,426,435,440,475,491,517,535,541,545,556]},{"collocation":"urban planning","score":234.5604283796,"doc_ids":[10,13,14,26,42,87,114,180,193,211,270,345,378,383,409,421,426,440,469,506,512,517,545]},{"collocation":"remote sensing","score":203.7051187655,"doc_ids":[90,245,313,364,365,378,389,469]},{"collocation":"random forest","score":148.5238268852,"doc_ids":[68,194,245,313,364,421,435,475,541]},{"collocation":"land cover","score":117.1911989574,"doc_ids":[68,90,245,313]},{"collocation":"social media","score":114.8860090433,"doc_ids":[13,14,65,92,426]},{"collocation":"image classification","score":111.2348174765,"doc_ids":[68,90,245,365,378]},{"collocation":"neural network","score":108.2173633541,"doc_ids":[211,389,426,440,475,506,535]},{"collocation":"urban environments","score":105.8330349224,"doc_ids":[13,194,268,359,365,516,535,552]},{"collocation":"landscape patterns","score":102.2354333268,"doc_ids":[10]}],"TopWords_pmi":[{"collocation":"crime count","score":11.9768027629,"doc_ids":[374]},{"collocation":"dar es","score":11.9768027629,"doc_ids":[238]},{"collocation":"es salaam","score":11.9768027629,"doc_ids":[238]},{"collocation":"geographically weighted","score":11.9768027629,"doc_ids":[10,345]},{"collocation":"rights reserved","score":11.9768027629,"doc_ids":[78,359,378]},{"collocation":"upper awash","score":11.9768027629,"doc_ids":[90]},{"collocation":"awash basin","score":11.2398371687,"doc_ids":[90]},{"collocation":"developing countries","score":11.2398371687,"doc_ids":[26,78,421]},{"collocation":"normalized difference","score":11.1467277643,"doc_ids":[330,345]},{"collocation":"blue unit","score":10.9768027629,"doc_ids":[552]}]},{"Cluster":8,"NumDocs":31,"DocIds":[43,45,91,133,139,152,163,169,186,187,207,247,249,260,276,277,327,340,343,392,404,425,457,486,493,527,573,576,584,585,586],"TopWords_chi":[{"collocation":"stream water","score":6094.0,"doc_ids":[247]},{"collocation":"contain papers","score":4874.3994745484,"doc_ids":[573,584,585,586]},{"collocation":"machine learning","score":4765.0688575864,"doc_ids":[43,45,133,152,163,187,207,247,260,277,340,392,404,425,457,493,527,573,584,585,586]},{"collocation":"semantic segmentation","score":4685.3808223335,"doc_ids":[249,486]},{"collocation":"discussed include","score":4569.7496306025,"doc_ids":[573,584,586]},{"collocation":"topics discussed","score":4569.7496306025,"doc_ids":[573,584,586]},{"collocation":"track contributions","score":4569.7496306025,"doc_ids":[585]},{"collocation":"random forest","score":4351.427398353,"doc_ids":[247,340,425]},{"collocation":"occupant behaviour","score":3898.5588505208,"doc_ids":[169]},{"collocation":"proceedings contain","score":3898.5588505208,"doc_ids":[573,584,585,586]}],"TopWords_likelihood":[{"collocation":"machine learning","score":367.720226035,"doc_ids":[43,45,133,152,163,187,207,247,260,277,340,392,404,425,457,493,527,573,584,585,586]},{"collocation":"semantic segmentation","score":134.1877710625,"doc_ids":[249,486]},{"collocation":"stream water","score":122.159387954,"doc_ids":[247]},{"collocation":"urban planning","score":111.302585835,"doc_ids":[43,186,187,207,249,276,277,327,340,343,392,404,486,576,586]},{"collocation":"water quality","score":104.8361484512,"doc_ids":[247]},{"collocation":"street greenery","score":87.4273016746,"doc_ids":[91]},{"collocation":"surface temperature","score":87.0100281711,"doc_ids":[45]},{"collocation":"neural network","score":84.7888759629,"doc_ids":[139,163,186,327,493]},{"collocation":"random forest","score":72.6763427127,"doc_ids":[247,340,425]},{"collocation":"contain papers","score":61.6234744441,"doc_ids":[573,584,585,586]}],"TopWords_pmi":[{"collocation":"discussed include","score":10.5731737847,"doc_ids":[573,584,586]},{"collocation":"topics discussed","score":10.5731737847,"doc_ids":[573,584,586]},{"collocation":"track contributions","score":10.5731737847,"doc_ids":[585]},{"collocation":"contain papers","score":10.2512456898,"doc_ids":[573,584,585,586]},{"collocation":"randomly selected","score":10.2512456898,"doc_ids":[133]},{"collocation":"scenario tests","score":10.1581362854,"doc_ids":[133]},{"collocation":"aerial videos","score":9.988211284,"doc_ids":[486]},{"collocation":"occupant behaviour","score":9.9293175949,"doc_ids":[169]},{"collocation":"proceedings contain","score":9.9293175949,"doc_ids":[573,584,585,586]},{"collocation":"daily accessed","score":9.8362081905,"doc_ids":[91]}]},{"Cluster":9,"NumDocs":12,"DocIds":[54,79,151,162,213,266,279,290,357,358,361,509],"TopWords_chi":[{"collocation":"health monitoring","score":2630.0,"doc_ids":[266]},{"collocation":"machine learning","score":2630.0,"doc_ids":[54,79,151,162,213,266,290,361]},{"collocation":"remote sensing","score":2630.0,"doc_ids":[54,361]},{"collocation":"rights reserved","score":2630.0,"doc_ids":[279,357,358]},{"collocation":"residential segregation","score":1971.7491435097,"doc_ids":[290]},{"collocation":"structural health","score":1971.7491435097,"doc_ids":[266]},{"collocation":"land cover","score":1970.996570122,"doc_ids":[361]},{"collocation":"built environment","score":1312.9969535415,"doc_ids":[213,290]},{"collocation":"utility computing","score":1312.9969535415,"doc_ids":[266]},{"collocation":"environmental conditions","score":1181.5475066188,"doc_ids":[79]}],"TopWords_likelihood":[{"collocation":"machine learning","score":184.9149532808,"doc_ids":[54,79,151,162,213,266,290,361]},{"collocation":"urban planning","score":121.652837021,"doc_ids":[54,213,266,279,361,509]},{"collocation":"land cover","score":75.9846949233,"doc_ids":[361]},{"collocation":"planning reform","score":57.1743880894,"doc_ids":[509]},{"collocation":"nlos multipath","score":55.3202608915,"doc_ids":[358]},{"collocation":"uav images","score":51.9085199889,"doc_ids":[361]},{"collocation":"built environment","score":48.8111164867,"doc_ids":[213,290]},{"collocation":"utility computing","score":48.8111164867,"doc_ids":[266]},{"collocation":"health monitoring","score":46.6533376639,"doc_ids":[266]},{"collocation":"remote sensing","score":46.6533376639,"doc_ids":[54,361]}],"TopWords_pmi":[{"collocation":"health monitoring","score":9.7758845835,"doc_ids":[266]},{"collocation":"remote sensing","score":9.7758845835,"doc_ids":[54,361]},{"collocation":"rights reserved","score":9.7758845835,"doc_ids":[279,357,358]},{"collocation":"residential segregation","score":9.3608470842,"doc_ids":[290]},{"collocation":"structural health","score":9.3608470842,"doc_ids":[266]},{"collocation":"environmental conditions","score":8.62388149,"doc_ids":[79]},{"collocation":"artificial intelligence","score":8.5534921621,"doc_ids":[357,509]},{"collocation":"land cover","score":8.3608470842,"doc_ids":[361]},{"collocation":"built environment","score":8.3608470842,"doc_ids":[213,290]},{"collocation":"utility computing","score":8.3608470842,"doc_ids":[266]}]},{"Cluster":10,"NumDocs":44,"DocIds":[12,31,32,39,64,81,86,117,126,174,192,202,232,257,259,263,264,269,283,295,302,309,333,349,368,370,373,391,396,403,408,416,418,441,446,447,495,510,511,519,528,540,549,577],"TopWords_chi":[{"collocation":"contain papers","score":9433.0,"doc_ids":[519,549,577]},{"collocation":"trunk circumference","score":9433.0,"doc_ids":[349]},{"collocation":"western cape","score":7859.999558054,"doc_ids":[408]},{"collocation":"machine learning","score":7601.2327501376,"doc_ids":[12,31,39,64,86,174,192,202,232,257,259,263,264,269,295,302,309,333,368,370,373,391,403,416,441,446,447,528,540,549,577]},{"collocation":"retail store","score":7545.5996606215,"doc_ids":[373]},{"collocation":"proceedings contain","score":7073.9997613998,"doc_ids":[519,549,577]},{"collocation":"store placement","score":7073.9997613998,"doc_ids":[373]},{"collocation":"international workshop","score":7073.2490452954,"doc_ids":[577]},{"collocation":"forest mla","score":5658.5996182397,"doc_ids":[447]},{"collocation":"planned special","score":5388.5707013318,"doc_ids":[295]}],"TopWords_likelihood":[{"collocation":"machine learning","score":608.6176390766,"doc_ids":[12,31,39,64,86,174,192,202,232,257,259,263,264,269,295,302,309,333,368,370,373,391,403,416,441,446,447,528,540,549,577]},{"collocation":"urban planning","score":115.20724325,"doc_ids":[32,117,126,174,257,264,302,309,368,370,396,416,446,511,528,540]},{"collocation":"international workshop","score":91.3213403605,"doc_ids":[577]},{"collocation":"functional zones","score":90.9077579099,"doc_ids":[32,174]},{"collocation":"road traffic","score":88.3607909285,"doc_ids":[295,408]},{"collocation":"support vector","score":83.6831703409,"doc_ids":[81,174,309,396]},{"collocation":"traffic safety","score":82.1386071331,"doc_ids":[408]},{"collocation":"western cape","score":80.015930217,"doc_ids":[408]},{"collocation":"artificial neural","score":79.178306078,"doc_ids":[12,81,391]},{"collocation":"neural networks","score":75.5548037872,"doc_ids":[12,81,309,391]}],"TopWords_pmi":[{"collocation":"contain papers","score":11.6185384516,"doc_ids":[519,549,577]},{"collocation":"trunk circumference","score":11.6185384516,"doc_ids":[349]},{"collocation":"proceedings contain","score":11.2035009524,"doc_ids":[519,549,577]},{"collocation":"store placement","score":11.2035009524,"doc_ids":[373]},{"collocation":"forest mla","score":10.8815728575,"doc_ids":[447]},{"collocation":"retail store","score":10.8815728575,"doc_ids":[373]},{"collocation":"impervious surfaces","score":10.6185384516,"doc_ids":[126]},{"collocation":"monetary poverty","score":10.6185384516,"doc_ids":[263]},{"collocation":"western cape","score":10.6185384516,"doc_ids":[408]},{"collocation":"planned special","score":10.3961460303,"doc_ids":[295]}]},{"Cluster":11,"NumDocs":31,"DocIds":[23,27,38,41,44,88,94,97,100,113,150,156,164,178,198,205,212,254,256,285,329,348,355,413,420,423,478,492,498,571,579],"TopWords_chi":[{"collocation":"colour infrared","score":6635.0,"doc_ids":[150]},{"collocation":"computer vision","score":6635.0,"doc_ids":[41,88,178,423]},{"collocation":"highway unit","score":6635.0,"doc_ids":[178]},{"collocation":"las vegas","score":6635.0,"doc_ids":[492]},{"collocation":"mob recursive","score":6635.0,"doc_ids":[413]},{"collocation":"online reviews","score":6635.0,"doc_ids":[492]},{"collocation":"recursive partitioning","score":6635.0,"doc_ids":[413]},{"collocation":"remote sensing","score":6635.0,"doc_ids":[27,113,150,156,178,413]},{"collocation":"mosquito occurrence","score":5528.3327048768,"doc_ids":[413]},{"collocation":"multilayer perceptron","score":4975.4996607358,"doc_ids":[38,113]}],"TopWords_likelihood":[{"collocation":"machine learning","score":210.0634314882,"doc_ids":[27,44,113,150,178,205,212,254,329,413,420,423,492]},{"collocation":"computer vision","score":188.0887916833,"doc_ids":[41,88,178,423]},{"collocation":"remote sensing","score":109.9514654903,"doc_ids":[27,113,150,156,178,413]},{"collocation":"urban planning","score":92.9559979075,"doc_ids":[27,41,100,113,156,164,178,198,254,329,348,413,571]},{"collocation":"colour infrared","score":81.902991499,"doc_ids":[150]},{"collocation":"pedestrian activity","score":76.8941717994,"doc_ids":[97]},{"collocation":"mosquito occurrence","score":76.4962569926,"doc_ids":[413]},{"collocation":"building footprints","score":75.9044763115,"doc_ids":[156]},{"collocation":"land cover","score":75.6608243803,"doc_ids":[113,178]},{"collocation":"smart cities","score":74.7067233493,"doc_ids":[44,94,285,420]}],"TopWords_pmi":[{"collocation":"las vegas","score":11.1109182495,"doc_ids":[492]},{"collocation":"mob recursive","score":11.1109182495,"doc_ids":[413]},{"collocation":"online reviews","score":11.1109182495,"doc_ids":[492]},{"collocation":"recursive partitioning","score":11.1109182495,"doc_ids":[413]},{"collocation":"highway unit","score":10.6958807503,"doc_ids":[178]},{"collocation":"multilayer perceptron","score":10.6958807503,"doc_ids":[38,113]},{"collocation":"air pollutant","score":10.3739526554,"doc_ids":[348]},{"collocation":"colour infrared","score":10.3739526554,"doc_ids":[150]},{"collocation":"random forest","score":10.280843251,"doc_ids":[113,178,413]},{"collocation":"block level","score":10.1109182495,"doc_ids":[41]}]},{"Cluster":12,"NumDocs":31,"DocIds":[8,22,28,49,73,74,95,103,130,142,154,159,172,201,234,240,243,292,293,305,398,428,455,484,521,559,575,582,589,593,594],"TopWords_chi":[{"collocation":"south korea","score":7857.0,"doc_ids":[28,234]},{"collocation":"remote sensing","score":6426.8163052544,"doc_ids":[49,292,428,521,575]},{"collocation":"point clouds","score":5891.9997135218,"doc_ids":[455]},{"collocation":"yunyang county","score":5891.9997135218,"doc_ids":[130]},{"collocation":"support vector","score":5891.2488536492,"doc_ids":[8,240,428,455,575]},{"collocation":"intelligent computation","score":5497.7981273885,"doc_ids":[594]},{"collocation":"random forest","score":5236.6659875207,"doc_ids":[8,28,130]},{"collocation":"built environment","score":4817.4496538297,"doc_ids":[22,73,103,589]},{"collocation":"machine learning","score":4803.5162222027,"doc_ids":[22,28,74,95,103,130,142,154,159,240,292,293,428,455,521,559,575,582]},{"collocation":"urbanization process","score":4423.1797070213,"doc_ids":[293,594]}],"TopWords_likelihood":[{"collocation":"machine learning","score":271.1137310393,"doc_ids":[22,28,74,95,103,130,142,154,159,240,292,293,428,455,521,559,575,582]},{"collocation":"land use","score":186.1969854388,"doc_ids":[49,73,74,103,484,589,594]},{"collocation":"urbanization process","score":173.1266246229,"doc_ids":[293,594]},{"collocation":"urban planning","score":150.4792244656,"doc_ids":[28,49,130,172,201,234,243,292,293,305,428,455,484,521,575,589,593,594]},{"collocation":"remote sensing","score":129.4534619009,"doc_ids":[49,292,428,521,575]},{"collocation":"built environment","score":115.9589479693,"doc_ids":[22,73,103,589]},{"collocation":"lucc analog","score":101.9335205246,"doc_ids":[594]},{"collocation":"intelligent computation","score":100.1019754067,"doc_ids":[594]},{"collocation":"complexity science","score":94.2195537639,"doc_ids":[594]},{"collocation":"support vector","score":89.1268625852,"doc_ids":[8,240,428,455,575]}],"TopWords_pmi":[{"collocation":"south korea","score":11.3548003444,"doc_ids":[28,234]},{"collocation":"point clouds","score":10.9397628451,"doc_ids":[455]},{"collocation":"yunyang county","score":10.9397628451,"doc_ids":[130]},{"collocation":"random forest","score":10.3548003444,"doc_ids":[8,28,130]},{"collocation":"genetic algorithms","score":10.2027972509,"doc_ids":[594]},{"collocation":"linear regression","score":10.132407923,"doc_ids":[8,49,159]},{"collocation":"neighborhood scale","score":9.9397628451,"doc_ids":[95]},{"collocation":"predictive analytics","score":9.9397628451,"doc_ids":[142]},{"collocation":"support vector","score":9.9397628451,"doc_ids":[8,240,428,455,575]},{"collocation":"total esv","score":9.9397628451,"doc_ids":[49]}]},{"Cluster":13,"NumDocs":49,"DocIds":[3,6,33,46,93,128,189,218,229,230,265,275,278,280,284,288,304,307,319,336,367,376,386,402,414,432,433,477,481,488,494,499,500,513,514,515,518,524,529,532,533,544,546,548,551,558,562,564,580],"TopWords_chi":[{"collocation":"baru station","score":10036.0,"doc_ids":[562]},{"collocation":"depok baru","score":10036.0,"doc_ids":[562]},{"collocation":"gradient boosting","score":10036.0,"doc_ids":[189,280]},{"collocation":"montevideo uruguay","score":10036.0,"doc_ids":[533]},{"collocation":"remotely sensed","score":10036.0,"doc_ids":[488,532,548]},{"collocation":"rights reserved","score":10036.0,"doc_ids":[278,288,367,386,481,515,529,546,580]},{"collocation":"heat island","score":8027.9996810207,"doc_ids":[414,580]},{"collocation":"machine learning","score":6928.3546361864,"doc_ids":[6,46,93,128,265,278,280,284,288,307,319,336,367,386,414,432,481,488,494,499,513,515,518,532,533,548,551,564,580]},{"collocation":"remote sensing","score":6689.3328017012,"doc_ids":[3,548,551,564]},{"collocation":"drone futures","score":6421.439302213,"doc_ids":[230]}],"TopWords_likelihood":[{"collocation":"machine learning","score":452.3456961112,"doc_ids":[6,46,93,128,265,278,280,284,288,307,319,336,367,386,414,432,481,488,494,499,513,515,518,532,533,548,551,564,580]},{"collocation":"urban planning","score":225.7986760928,"doc_ids":[3,33,189,229,265,275,278,307,336,367,376,386,402,414,432,477,481,488,494,499,500,514,524,529,544,548,558,562,564]},{"collocation":"land cover","score":167.7165919155,"doc_ids":[532,548,564,580]},{"collocation":"rights reserved","score":144.2926945844,"doc_ids":[278,288,367,386,481,515,529,546,580]},{"collocation":"neural network","score":116.6551845681,"doc_ids":[46,229,367,386,488,532,544,546]},{"collocation":"human mobility","score":115.59596524,"doc_ids":[33,284,477]},{"collocation":"social media","score":105.4148823576,"doc_ids":[46,494]},{"collocation":"health hazard","score":92.6948352495,"doc_ids":[46]},{"collocation":"life circle","score":85.9043022111,"doc_ids":[336]},{"collocation":"cover classification","score":74.4936476514,"doc_ids":[548,580]}],"TopWords_pmi":[{"collocation":"baru station","score":11.7079342547,"doc_ids":[562]},{"collocation":"depok baru","score":11.7079342547,"doc_ids":[562]},{"collocation":"gradient boosting","score":11.7079342547,"doc_ids":[189,280]},{"collocation":"montevideo uruguay","score":11.7079342547,"doc_ids":[533]},{"collocation":"remotely sensed","score":11.7079342547,"doc_ids":[488,532,548]},{"collocation":"heat island","score":10.9709686605,"doc_ids":[414,580]},{"collocation":"signal reception","score":10.8778592561,"doc_ids":[280]},{"collocation":"remote sensing","score":10.7079342547,"doc_ids":[3,548,551,564]},{"collocation":"drone futures","score":10.6490405656,"doc_ids":[230]},{"collocation":"cognitive computing","score":10.5559311612,"doc_ids":[288]}]},{"Cluster":14,"NumDocs":34,"DocIds":[50,77,96,102,106,116,123,131,141,158,161,179,190,199,226,231,251,282,289,311,332,335,354,369,371,372,382,448,452,467,490,561,565,566],"TopWords_chi":[{"collocation":"commercial increment","score":7684.0,"doc_ids":[565]},{"collocation":"earth observation","score":7684.0,"doc_ids":[251,565]},{"collocation":"zhanggong district","score":7684.0,"doc_ids":[96]},{"collocation":"thermal comfort","score":6402.4994573946,"doc_ids":[179]},{"collocation":"routing schemes","score":5762.2497070694,"doc_ids":[311]},{"collocation":"artificial intelligence","score":4479.4140072077,"doc_ids":[231,282,354,565]},{"collocation":"remote sensing","score":4275.1670691018,"doc_ids":[251,332,382,565]},{"collocation":"mobile phone","score":4188.5433233086,"doc_ids":[371]},{"collocation":"machine learning","score":4095.1328135895,"doc_ids":[50,77,102,106,141,158,161,190,251,282,289,311,335,369,382,448,452,561,566]},{"collocation":"input representations","score":3510.1699739351,"doc_ids":[448]}],"TopWords_likelihood":[{"collocation":"machine learning","score":326.2273668759,"doc_ids":[50,77,102,106,141,158,161,190,251,282,289,311,335,369,382,448,452,561,566]},{"collocation":"land use","score":223.5807576314,"doc_ids":[77,96,102,131,332,335]},{"collocation":"land cover","score":148.5267758354,"doc_ids":[77,102,332,382]},{"collocation":"transportation mode","score":104.0629093121,"doc_ids":[161,335]},{"collocation":"artificial intelligence","score":95.7067780395,"doc_ids":[231,282,354,565]},{"collocation":"remote sensing","score":91.5595372306,"doc_ids":[251,332,382,565]},{"collocation":"big data","score":91.4011788864,"doc_ids":[106,251,282,335,565]},{"collocation":"mode recognition","score":83.4934018123,"doc_ids":[161]},{"collocation":"earth observation","score":83.3713218948,"doc_ids":[251,565]},{"collocation":"mobile phone","score":82.6987431297,"doc_ids":[371]}],"TopWords_pmi":[{"collocation":"commercial increment","score":11.3226793029,"doc_ids":[565]},{"collocation":"zhanggong district","score":11.3226793029,"doc_ids":[96]},{"collocation":"routing schemes","score":10.9076418037,"doc_ids":[311]},{"collocation":"earth observation","score":10.5857137088,"doc_ids":[251,565]},{"collocation":"thermal comfort","score":10.3226793029,"doc_ids":[179]},{"collocation":"climate resilience","score":10.1706762095,"doc_ids":[467]},{"collocation":"mean absolute","score":10.1002868816,"doc_ids":[199,226]},{"collocation":"socioeconomic indicators","score":10.1002868816,"doc_ids":[372]},{"collocation":"vehicle selection","score":9.9076418037,"doc_ids":[123]},{"collocation":"input representations","score":9.7783587867,"doc_ids":[448]}]}]