[{"dimension":15,"min_samples":"None","min_cluster_size":"5","epsilon":"0.0","total_clusters":14,"outliers":226,"Silhouette_score":0.598810153,"cluster_results":[{"cluster_no":3,"count":5},{"cluster_no":10,"count":6},{"cluster_no":6,"count":7},{"cluster_no":0,"count":11},{"cluster_no":8,"count":14},{"cluster_no":12,"count":14},{"cluster_no":9,"count":17},{"cluster_no":2,"count":20},{"cluster_no":7,"count":20},{"cluster_no":11,"count":30},{"cluster_no":1,"count":49},{"cluster_no":4,"count":55},{"cluster_no":5,"count":110},{"cluster_no":-1,"count":226}]},{"dimension":15,"min_samples":"None","min_cluster_size":"6","epsilon":"0.0","total_clusters":10,"outliers":212,"Silhouette_score":0.6603551164,"cluster_results":[{"cluster_no":0,"count":11},{"cluster_no":6,"count":13},{"cluster_no":5,"count":21},{"cluster_no":8,"count":29},{"cluster_no":2,"count":45},{"cluster_no":1,"count":51},{"cluster_no":3,"count":52},{"cluster_no":7,"count":53},{"cluster_no":4,"count":97},{"cluster_no":-1,"count":212}]},{"dimension":15,"min_samples":"None","min_cluster_size":"7","epsilon":"0.0","total_clusters":10,"outliers":236,"Silhouette_score":0.6741225394,"cluster_results":[{"cluster_no":2,"count":11},{"cluster_no":3,"count":13},{"cluster_no":6,"count":22},{"cluster_no":8,"count":27},{"cluster_no":1,"count":41},{"cluster_no":0,"count":46},{"cluster_no":4,"count":49},{"cluster_no":7,"count":53},{"cluster_no":5,"count":86},{"cluster_no":-1,"count":236}]},{"dimension":15,"min_samples":"None","min_cluster_size":"8","epsilon":"0.0","total_clusters":10,"outliers":264,"Silhouette_score":0.6997331599,"cluster_results":[{"cluster_no":3,"count":11},{"cluster_no":2,"count":12},{"cluster_no":4,"count":21},{"cluster_no":6,"count":29},{"cluster_no":1,"count":39},{"cluster_no":0,"count":46},{"cluster_no":7,"count":46},{"cluster_no":5,"count":50},{"cluster_no":8,"count":66},{"cluster_no":-1,"count":264}]},{"dimension":15,"min_samples":"None","min_cluster_size":"9","epsilon":"0.0","total_clusters":10,"outliers":271,"Silhouette_score":0.7050912629,"cluster_results":[{"cluster_no":2,"count":10},{"cluster_no":3,"count":11},{"cluster_no":4,"count":23},{"cluster_no":6,"count":28},{"cluster_no":1,"count":38},{"cluster_no":7,"count":45},{"cluster_no":0,"count":46},{"cluster_no":5,"count":51},{"cluster_no":8,"count":61},{"cluster_no":-1,"count":271}]},{"dimension":15,"min_samples":"None","min_cluster_size":"10","epsilon":"0.0","total_clusters":10,"outliers":277,"Silhouette_score":0.7189145057,"cluster_results":[{"cluster_no":2,"count":11},{"cluster_no":4,"count":11},{"cluster_no":3,"count":22},{"cluster_no":6,"count":30},{"cluster_no":1,"count":37},{"cluster_no":7,"count":43},{"cluster_no":0,"count":45},{"cluster_no":5,"count":48},{"cluster_no":8,"count":60},{"cluster_no":-1,"count":277}]},{"dimension":15,"min_samples":"None","min_cluster_size":"11","epsilon":"0.0","total_clusters":4,"outliers":128,"Silhouette_score":-0.1520630663,"cluster_results":[{"cluster_no":0,"count":42},{"cluster_no":2,"count":46},{"cluster_no":-1,"count":128},{"cluster_no":1,"count":368}]},{"dimension":15,"min_samples":"None","min_cluster_size":"12","epsilon":"0.0","total_clusters":4,"outliers":140,"Silhouette_score":-0.1452589358,"cluster_results":[{"cluster_no":0,"count":41},{"cluster_no":2,"count":46},{"cluster_no":-1,"count":140},{"cluster_no":1,"count":357}]},{"dimension":15,"min_samples":"None","min_cluster_size":"13","epsilon":"0.0","total_clusters":4,"outliers":146,"Silhouette_score":-0.1460390927,"cluster_results":[{"cluster_no":0,"count":40},{"cluster_no":2,"count":46},{"cluster_no":-1,"count":146},{"cluster_no":1,"count":352}]},{"dimension":15,"min_samples":"None","min_cluster_size":"14","epsilon":"0.0","total_clusters":4,"outliers":159,"Silhouette_score":-0.1516602434,"cluster_results":[{"cluster_no":2,"count":36},{"cluster_no":0,"count":44},{"cluster_no":-1,"count":159},{"cluster_no":1,"count":345}]},{"dimension":15,"min_samples":"None","min_cluster_size":"15","epsilon":"0.0","total_clusters":6,"outliers":238,"Silhouette_score":0.6307143101,"cluster_results":[{"cluster_no":4,"count":19},{"cluster_no":1,"count":34},{"cluster_no":0,"count":44},{"cluster_no":3,"count":92},{"cluster_no":2,"count":157},{"cluster_no":-1,"count":238}]},{"dimension":15,"min_samples":"1","min_cluster_size":"5","epsilon":"0.0","total_clusters":42,"outliers":162,"Silhouette_score":0.5395329923,"cluster_results":[{"cluster_no":0,"count":5},{"cluster_no":7,"count":5},{"cluster_no":14,"count":5},{"cluster_no":17,"count":5},{"cluster_no":21,"count":5},{"cluster_no":25,"count":5},{"cluster_no":9,"count":6},{"cluster_no":3,"count":7},{"cluster_no":4,"count":7},{"cluster_no":10,"count":7},{"cluster_no":11,"count":7},{"cluster_no":12,"count":7},{"cluster_no":13,"count":7},{"cluster_no":15,"count":7},{"cluster_no":19,"count":7},{"cluster_no":29,"count":7},{"cluster_no":37,"count":7},{"cluster_no":8,"count":8},{"cluster_no":20,"count":8},{"cluster_no":26,"count":8},{"cluster_no":35,"count":8},{"cluster_no":2,"count":9},{"cluster_no":30,"count":9},{"cluster_no":32,"count":9},{"cluster_no":36,"count":9},{"cluster_no":38,"count":10},{"cluster_no":40,"count":10},{"cluster_no":24,"count":11},{"cluster_no":1,"count":12},{"cluster_no":28,"count":12},{"cluster_no":18,"count":13},{"cluster_no":39,"count":13},{"cluster_no":5,"count":14},{"cluster_no":16,"count":15},{"cluster_no":6,"count":16},{"cluster_no":34,"count":16},{"cluster_no":22,"count":19},{"cluster_no":23,"count":20},{"cluster_no":27,"count":20},{"cluster_no":33,"count":23},{"cluster_no":31,"count":24},{"cluster_no":-1,"count":162}]},{"dimension":15,"min_samples":"1","min_cluster_size":"6","epsilon":"0.0","total_clusters":34,"outliers":172,"Silhouette_score":0.4988928775,"cluster_results":[{"cluster_no":5,"count":6},{"cluster_no":3,"count":7},{"cluster_no":6,"count":7},{"cluster_no":7,"count":7},{"cluster_no":8,"count":7},{"cluster_no":10,"count":7},{"cluster_no":11,"count":7},{"cluster_no":13,"count":7},{"cluster_no":21,"count":7},{"cluster_no":29,"count":7},{"cluster_no":4,"count":8},{"cluster_no":14,"count":8},{"cluster_no":18,"count":8},{"cluster_no":27,"count":8},{"cluster_no":2,"count":9},{"cluster_no":22,"count":9},{"cluster_no":24,"count":9},{"cluster_no":28,"count":9},{"cluster_no":30,"count":10},{"cluster_no":32,"count":10},{"cluster_no":17,"count":11},{"cluster_no":0,"count":12},{"cluster_no":20,"count":12},{"cluster_no":12,"count":13},{"cluster_no":31,"count":13},{"cluster_no":26,"count":16},{"cluster_no":15,"count":19},{"cluster_no":16,"count":20},{"cluster_no":19,"count":20},{"cluster_no":9,"count":22},{"cluster_no":25,"count":23},{"cluster_no":23,"count":24},{"cluster_no":1,"count":50},{"cluster_no":-1,"count":172}]},{"dimension":15,"min_samples":"1","min_cluster_size":"7","epsilon":"0.0","total_clusters":32,"outliers":169,"Silhouette_score":0.4895423863,"cluster_results":[{"cluster_no":3,"count":7},{"cluster_no":6,"count":7},{"cluster_no":7,"count":7},{"cluster_no":9,"count":7},{"cluster_no":10,"count":7},{"cluster_no":12,"count":7},{"cluster_no":19,"count":7},{"cluster_no":27,"count":7},{"cluster_no":5,"count":8},{"cluster_no":13,"count":8},{"cluster_no":18,"count":8},{"cluster_no":25,"count":8},{"cluster_no":2,"count":9},{"cluster_no":20,"count":9},{"cluster_no":22,"count":9},{"cluster_no":26,"count":9},{"cluster_no":28,"count":10},{"cluster_no":30,"count":10},{"cluster_no":17,"count":11},{"cluster_no":0,"count":12},{"cluster_no":4,"count":13},{"cluster_no":11,"count":13},{"cluster_no":29,"count":13},{"cluster_no":24,"count":16},{"cluster_no":15,"count":19},{"cluster_no":16,"count":20},{"cluster_no":8,"count":22},{"cluster_no":23,"count":23},{"cluster_no":21,"count":24},{"cluster_no":14,"count":35},{"cluster_no":1,"count":50},{"cluster_no":-1,"count":169}]},{"dimension":15,"min_samples":"1","min_cluster_size":"8","epsilon":"0.0","total_clusters":24,"outliers":211,"Silhouette_score":0.5141363238,"cluster_results":[{"cluster_no":5,"count":8},{"cluster_no":7,"count":8},{"cluster_no":12,"count":8},{"cluster_no":18,"count":8},{"cluster_no":2,"count":9},{"cluster_no":13,"count":9},{"cluster_no":15,"count":9},{"cluster_no":19,"count":9},{"cluster_no":20,"count":10},{"cluster_no":22,"count":10},{"cluster_no":11,"count":11},{"cluster_no":0,"count":12},{"cluster_no":3,"count":13},{"cluster_no":6,"count":13},{"cluster_no":21,"count":13},{"cluster_no":17,"count":16},{"cluster_no":9,"count":19},{"cluster_no":10,"count":20},{"cluster_no":16,"count":23},{"cluster_no":14,"count":24},{"cluster_no":8,"count":35},{"cluster_no":4,"count":36},{"cluster_no":1,"count":50},{"cluster_no":-1,"count":211}]},{"dimension":15,"min_samples":"1","min_cluster_size":"9","epsilon":"0.0","total_clusters":17,"outliers":184,"Silhouette_score":0.526198523,"cluster_results":[{"cluster_no":2,"count":9},{"cluster_no":11,"count":9},{"cluster_no":13,"count":9},{"cluster_no":9,"count":11},{"cluster_no":0,"count":12},{"cluster_no":4,"count":13},{"cluster_no":5,"count":13},{"cluster_no":7,"count":19},{"cluster_no":8,"count":20},{"cluster_no":14,"count":23},{"cluster_no":12,"count":24},{"cluster_no":15,"count":31},{"cluster_no":6,"count":35},{"cluster_no":1,"count":50},{"cluster_no":3,"count":51},{"cluster_no":10,"count":71},{"cluster_no":-1,"count":184}]},{"dimension":15,"min_samples":"1","min_cluster_size":"10","epsilon":"0.0","total_clusters":14,"outliers":151,"Silhouette_score":0.555311119,"cluster_results":[{"cluster_no":10,"count":11},{"cluster_no":0,"count":12},{"cluster_no":3,"count":13},{"cluster_no":5,"count":13},{"cluster_no":8,"count":19},{"cluster_no":9,"count":20},{"cluster_no":11,"count":23},{"cluster_no":12,"count":31},{"cluster_no":7,"count":35},{"cluster_no":6,"count":44},{"cluster_no":1,"count":50},{"cluster_no":2,"count":51},{"cluster_no":4,"count":111},{"cluster_no":-1,"count":151}]},{"dimension":15,"min_samples":"1","min_cluster_size":"11","epsilon":"0.0","total_clusters":14,"outliers":151,"Silhouette_score":0.555311119,"cluster_results":[{"cluster_no":10,"count":11},{"cluster_no":0,"count":12},{"cluster_no":3,"count":13},{"cluster_no":5,"count":13},{"cluster_no":8,"count":19},{"cluster_no":9,"count":20},{"cluster_no":11,"count":23},{"cluster_no":12,"count":31},{"cluster_no":7,"count":35},{"cluster_no":6,"count":44},{"cluster_no":1,"count":50},{"cluster_no":2,"count":51},{"cluster_no":4,"count":111},{"cluster_no":-1,"count":151}]},{"dimension":15,"min_samples":"1","min_cluster_size":"12","epsilon":"0.0","total_clusters":13,"outliers":142,"Silhouette_score":0.5325949931,"cluster_results":[{"cluster_no":0,"count":12},{"cluster_no":3,"count":13},{"cluster_no":6,"count":13},{"cluster_no":9,"count":19},{"cluster_no":10,"count":23},{"cluster_no":11,"count":31},{"cluster_no":8,"count":35},{"cluster_no":5,"count":40},{"cluster_no":7,"count":44},{"cluster_no":1,"count":50},{"cluster_no":2,"count":51},{"cluster_no":4,"count":111},{"cluster_no":-1,"count":142}]},{"dimension":15,"min_samples":"1","min_cluster_size":"13","epsilon":"0.0","total_clusters":12,"outliers":154,"Silhouette_score":0.5513343576,"cluster_results":[{"cluster_no":2,"count":13},{"cluster_no":5,"count":13},{"cluster_no":8,"count":19},{"cluster_no":9,"count":23},{"cluster_no":10,"count":31},{"cluster_no":7,"count":35},{"cluster_no":4,"count":40},{"cluster_no":6,"count":44},{"cluster_no":0,"count":50},{"cluster_no":1,"count":51},{"cluster_no":3,"count":111},{"cluster_no":-1,"count":154}]},{"dimension":15,"min_samples":"1","min_cluster_size":"14","epsilon":"0.0","total_clusters":10,"outliers":163,"Silhouette_score":0.5696977997,"cluster_results":[{"cluster_no":6,"count":19},{"cluster_no":7,"count":23},{"cluster_no":8,"count":31},{"cluster_no":5,"count":35},{"cluster_no":4,"count":44},{"cluster_no":0,"count":50},{"cluster_no":1,"count":51},{"cluster_no":2,"count":57},{"cluster_no":3,"count":111},{"cluster_no":-1,"count":163}]},{"dimension":15,"min_samples":"1","min_cluster_size":"15","epsilon":"0.0","total_clusters":10,"outliers":163,"Silhouette_score":0.5696977997,"cluster_results":[{"cluster_no":6,"count":19},{"cluster_no":7,"count":23},{"cluster_no":8,"count":31},{"cluster_no":5,"count":35},{"cluster_no":4,"count":44},{"cluster_no":0,"count":50},{"cluster_no":1,"count":51},{"cluster_no":2,"count":57},{"cluster_no":3,"count":111},{"cluster_no":-1,"count":163}]},{"dimension":15,"min_samples":"2","min_cluster_size":"5","epsilon":"0.0","total_clusters":36,"outliers":204,"Silhouette_score":0.5511715528,"cluster_results":[{"cluster_no":3,"count":5},{"cluster_no":9,"count":5},{"cluster_no":12,"count":5},{"cluster_no":13,"count":5},{"cluster_no":17,"count":5},{"cluster_no":19,"count":5},{"cluster_no":31,"count":5},{"cluster_no":5,"count":6},{"cluster_no":7,"count":6},{"cluster_no":8,"count":6},{"cluster_no":11,"count":6},{"cluster_no":14,"count":6},{"cluster_no":23,"count":6},{"cluster_no":25,"count":6},{"cluster_no":2,"count":7},{"cluster_no":6,"count":7},{"cluster_no":20,"count":7},{"cluster_no":30,"count":7},{"cluster_no":4,"count":8},{"cluster_no":15,"count":8},{"cluster_no":29,"count":8},{"cluster_no":34,"count":8},{"cluster_no":22,"count":9},{"cluster_no":32,"count":9},{"cluster_no":33,"count":11},{"cluster_no":0,"count":12},{"cluster_no":10,"count":13},{"cluster_no":18,"count":13},{"cluster_no":24,"count":13},{"cluster_no":27,"count":15},{"cluster_no":21,"count":19},{"cluster_no":16,"count":22},{"cluster_no":28,"count":22},{"cluster_no":26,"count":35},{"cluster_no":1,"count":50},{"cluster_no":-1,"count":204}]},{"dimension":15,"min_samples":"2","min_cluster_size":"6","epsilon":"0.0","total_clusters":29,"outliers":239,"Silhouette_score":0.5893370333,"cluster_results":[{"cluster_no":4,"count":6},{"cluster_no":6,"count":6},{"cluster_no":7,"count":6},{"cluster_no":9,"count":6},{"cluster_no":10,"count":6},{"cluster_no":17,"count":6},{"cluster_no":19,"count":6},{"cluster_no":2,"count":7},{"cluster_no":5,"count":7},{"cluster_no":14,"count":7},{"cluster_no":24,"count":7},{"cluster_no":3,"count":8},{"cluster_no":11,"count":8},{"cluster_no":23,"count":8},{"cluster_no":27,"count":8},{"cluster_no":16,"count":9},{"cluster_no":25,"count":9},{"cluster_no":26,"count":11},{"cluster_no":0,"count":12},{"cluster_no":8,"count":13},{"cluster_no":13,"count":13},{"cluster_no":18,"count":13},{"cluster_no":21,"count":15},{"cluster_no":15,"count":19},{"cluster_no":12,"count":22},{"cluster_no":22,"count":22},{"cluster_no":20,"count":35},{"cluster_no":1,"count":50},{"cluster_no":-1,"count":239}]},{"dimension":15,"min_samples":"2","min_cluster_size":"7","epsilon":"0.0","total_clusters":19,"outliers":215,"Silhouette_score":0.4801415818,"cluster_results":[{"cluster_no":2,"count":7},{"cluster_no":4,"count":7},{"cluster_no":11,"count":7},{"cluster_no":3,"count":8},{"cluster_no":6,"count":8},{"cluster_no":17,"count":8},{"cluster_no":13,"count":9},{"cluster_no":0,"count":12},{"cluster_no":9,"count":13},{"cluster_no":15,"count":15},{"cluster_no":12,"count":19},{"cluster_no":7,"count":22},{"cluster_no":16,"count":22},{"cluster_no":5,"count":27},{"cluster_no":8,"count":28},{"cluster_no":14,"count":35},{"cluster_no":1,"count":50},{"cluster_no":10,"count":72},{"cluster_no":-1,"count":215}]},{"dimension":15,"min_samples":"2","min_cluster_size":"8","epsilon":"0.0","total_clusters":16,"outliers":198,"Silhouette_score":0.5004406009,"cluster_results":[{"cluster_no":3,"count":8},{"cluster_no":5,"count":8},{"cluster_no":14,"count":8},{"cluster_no":10,"count":9},{"cluster_no":0,"count":12},{"cluster_no":8,"count":13},{"cluster_no":12,"count":15},{"cluster_no":9,"count":19},{"cluster_no":6,"count":22},{"cluster_no":13,"count":22},{"cluster_no":7,"count":28},{"cluster_no":2,"count":34},{"cluster_no":11,"count":35},{"cluster_no":1,"count":50},{"cluster_no":4,"count":103},{"cluster_no":-1,"count":198}]},{"dimension":15,"min_samples":"2","min_cluster_size":"9","epsilon":"0.0","total_clusters":13,"outliers":191,"Silhouette_score":0.599918256,"cluster_results":[{"cluster_no":9,"count":9},{"cluster_no":0,"count":12},{"cluster_no":6,"count":13},{"cluster_no":11,"count":15},{"cluster_no":8,"count":19},{"cluster_no":4,"count":22},{"cluster_no":5,"count":28},{"cluster_no":10,"count":35},{"cluster_no":7,"count":38},{"cluster_no":2,"count":49},{"cluster_no":1,"count":50},{"cluster_no":3,"count":103},{"cluster_no":-1,"count":191}]},{"dimension":15,"min_samples":"2","min_cluster_size":"10","epsilon":"0.0","total_clusters":12,"outliers":184,"Silhouette_score":0.595760854,"cluster_results":[{"cluster_no":0,"count":12},{"cluster_no":7,"count":13},{"cluster_no":10,"count":15},{"cluster_no":4,"count":22},{"cluster_no":5,"count":28},{"cluster_no":6,"count":35},{"cluster_no":9,"count":35},{"cluster_no":8,"count":38},{"cluster_no":2,"count":49},{"cluster_no":1,"count":50},{"cluster_no":3,"count":103},{"cluster_no":-1,"count":184}]},{"dimension":15,"min_samples":"2","min_cluster_size":"11","epsilon":"0.0","total_clusters":12,"outliers":184,"Silhouette_score":0.595760854,"cluster_results":[{"cluster_no":0,"count":12},{"cluster_no":7,"count":13},{"cluster_no":10,"count":15},{"cluster_no":4,"count":22},{"cluster_no":5,"count":28},{"cluster_no":6,"count":35},{"cluster_no":9,"count":35},{"cluster_no":8,"count":38},{"cluster_no":2,"count":49},{"cluster_no":1,"count":50},{"cluster_no":3,"count":103},{"cluster_no":-1,"count":184}]},{"dimension":15,"min_samples":"2","min_cluster_size":"12","epsilon":"0.0","total_clusters":11,"outliers":169,"Silhouette_score":0.5406866294,"cluster_results":[{"cluster_no":0,"count":12},{"cluster_no":6,"count":13},{"cluster_no":9,"count":15},{"cluster_no":5,"count":35},{"cluster_no":8,"count":35},{"cluster_no":7,"count":38},{"cluster_no":2,"count":49},{"cluster_no":1,"count":50},{"cluster_no":3,"count":65},{"cluster_no":4,"count":103},{"cluster_no":-1,"count":169}]},{"dimension":15,"min_samples":"2","min_cluster_size":"13","epsilon":"0.0","total_clusters":9,"outliers":177,"Silhouette_score":0.6068070608,"cluster_results":[{"cluster_no":5,"count":13},{"cluster_no":4,"count":35},{"cluster_no":7,"count":38},{"cluster_no":1,"count":49},{"cluster_no":0,"count":50},{"cluster_no":6,"count":54},{"cluster_no":2,"count":65},{"cluster_no":3,"count":103},{"cluster_no":-1,"count":177}]},{"dimension":15,"min_samples":"2","min_cluster_size":"14","epsilon":"0.0","total_clusters":8,"outliers":174,"Silhouette_score":0.6316301451,"cluster_results":[{"cluster_no":6,"count":38},{"cluster_no":1,"count":49},{"cluster_no":0,"count":50},{"cluster_no":4,"count":51},{"cluster_no":5,"count":54},{"cluster_no":2,"count":65},{"cluster_no":3,"count":103},{"cluster_no":-1,"count":174}]},{"dimension":15,"min_samples":"2","min_cluster_size":"15","epsilon":"0.0","total_clusters":8,"outliers":174,"Silhouette_score":0.6316301451,"cluster_results":[{"cluster_no":6,"count":38},{"cluster_no":1,"count":49},{"cluster_no":0,"count":50},{"cluster_no":4,"count":51},{"cluster_no":5,"count":54},{"cluster_no":2,"count":65},{"cluster_no":3,"count":103},{"cluster_no":-1,"count":174}]},{"dimension":15,"min_samples":"3","min_cluster_size":"5","epsilon":"0.0","total_clusters":27,"outliers":262,"Silhouette_score":0.6137402162,"cluster_results":[{"cluster_no":0,"count":5},{"cluster_no":5,"count":5},{"cluster_no":6,"count":5},{"cluster_no":22,"count":5},{"cluster_no":8,"count":6},{"cluster_no":9,"count":6},{"cluster_no":10,"count":6},{"cluster_no":16,"count":6},{"cluster_no":21,"count":6},{"cluster_no":2,"count":7},{"cluster_no":18,"count":7},{"cluster_no":23,"count":8},{"cluster_no":24,"count":8},{"cluster_no":25,"count":8},{"cluster_no":4,"count":9},{"cluster_no":11,"count":12},{"cluster_no":1,"count":13},{"cluster_no":20,"count":13},{"cluster_no":15,"count":14},{"cluster_no":7,"count":18},{"cluster_no":14,"count":18},{"cluster_no":12,"count":19},{"cluster_no":17,"count":19},{"cluster_no":13,"count":22},{"cluster_no":19,"count":31},{"cluster_no":3,"count":46},{"cluster_no":-1,"count":262}]},{"dimension":15,"min_samples":"3","min_cluster_size":"6","epsilon":"0.0","total_clusters":20,"outliers":218,"Silhouette_score":0.4371161645,"cluster_results":[{"cluster_no":6,"count":6},{"cluster_no":7,"count":6},{"cluster_no":9,"count":6},{"cluster_no":1,"count":7},{"cluster_no":16,"count":7},{"cluster_no":3,"count":9},{"cluster_no":4,"count":10},{"cluster_no":10,"count":12},{"cluster_no":0,"count":13},{"cluster_no":18,"count":13},{"cluster_no":14,"count":14},{"cluster_no":5,"count":18},{"cluster_no":13,"count":18},{"cluster_no":11,"count":19},{"cluster_no":15,"count":19},{"cluster_no":12,"count":22},{"cluster_no":17,"count":31},{"cluster_no":2,"count":46},{"cluster_no":8,"count":90},{"cluster_no":-1,"count":218}]},{"dimension":15,"min_samples":"3","min_cluster_size":"7","epsilon":"0.0","total_clusters":16,"outliers":209,"Silhouette_score":0.4671126474,"cluster_results":[{"cluster_no":1,"count":7},{"cluster_no":14,"count":7},{"cluster_no":4,"count":9},{"cluster_no":5,"count":10},{"cluster_no":8,"count":12},{"cluster_no":0,"count":13},{"cluster_no":12,"count":14},{"cluster_no":11,"count":18},{"cluster_no":9,"count":19},{"cluster_no":13,"count":19},{"cluster_no":10,"count":22},{"cluster_no":3,"count":35},{"cluster_no":2,"count":46},{"cluster_no":7,"count":54},{"cluster_no":6,"count":90},{"cluster_no":-1,"count":209}]},{"dimension":15,"min_samples":"3","min_cluster_size":"8","epsilon":"0.0","total_clusters":13,"outliers":185,"Silhouette_score":0.378791356,"cluster_results":[{"cluster_no":3,"count":9},{"cluster_no":4,"count":10},{"cluster_no":9,"count":12},{"cluster_no":0,"count":13},{"cluster_no":11,"count":14},{"cluster_no":10,"count":18},{"cluster_no":8,"count":31},{"cluster_no":2,"count":35},{"cluster_no":1,"count":53},{"cluster_no":7,"count":54},{"cluster_no":5,"count":60},{"cluster_no":6,"count":90},{"cluster_no":-1,"count":185}]},{"dimension":15,"min_samples":"3","min_cluster_size":"9","epsilon":"0.0","total_clusters":13,"outliers":185,"Silhouette_score":0.378791356,"cluster_results":[{"cluster_no":3,"count":9},{"cluster_no":4,"count":10},{"cluster_no":9,"count":12},{"cluster_no":0,"count":13},{"cluster_no":11,"count":14},{"cluster_no":10,"count":18},{"cluster_no":8,"count":31},{"cluster_no":2,"count":35},{"cluster_no":1,"count":53},{"cluster_no":7,"count":54},{"cluster_no":5,"count":60},{"cluster_no":6,"count":90},{"cluster_no":-1,"count":185}]},{"dimension":15,"min_samples":"3","min_cluster_size":"10","epsilon":"0.0","total_clusters":12,"outliers":183,"Silhouette_score":0.4152068898,"cluster_results":[{"cluster_no":3,"count":10},{"cluster_no":8,"count":12},{"cluster_no":0,"count":13},{"cluster_no":10,"count":14},{"cluster_no":9,"count":18},{"cluster_no":7,"count":31},{"cluster_no":2,"count":46},{"cluster_no":1,"count":53},{"cluster_no":6,"count":54},{"cluster_no":4,"count":60},{"cluster_no":5,"count":90},{"cluster_no":-1,"count":183}]},{"dimension":15,"min_samples":"3","min_cluster_size":"11","epsilon":"0.0","total_clusters":11,"outliers":193,"Silhouette_score":0.6018789059,"cluster_results":[{"cluster_no":7,"count":12},{"cluster_no":0,"count":13},{"cluster_no":9,"count":14},{"cluster_no":8,"count":18},{"cluster_no":6,"count":31},{"cluster_no":2,"count":46},{"cluster_no":1,"count":53},{"cluster_no":5,"count":54},{"cluster_no":3,"count":60},{"cluster_no":4,"count":90},{"cluster_no":-1,"count":193}]},{"dimension":15,"min_samples":"3","min_cluster_size":"12","epsilon":"0.0","total_clusters":11,"outliers":193,"Silhouette_score":0.6018789059,"cluster_results":[{"cluster_no":7,"count":12},{"cluster_no":0,"count":13},{"cluster_no":9,"count":14},{"cluster_no":8,"count":18},{"cluster_no":6,"count":31},{"cluster_no":2,"count":46},{"cluster_no":1,"count":53},{"cluster_no":5,"count":54},{"cluster_no":3,"count":60},{"cluster_no":4,"count":90},{"cluster_no":-1,"count":193}]},{"dimension":15,"min_samples":"3","min_cluster_size":"13","epsilon":"0.0","total_clusters":10,"outliers":205,"Silhouette_score":0.6142238698,"cluster_results":[{"cluster_no":0,"count":13},{"cluster_no":8,"count":14},{"cluster_no":7,"count":18},{"cluster_no":6,"count":31},{"cluster_no":2,"count":46},{"cluster_no":1,"count":53},{"cluster_no":5,"count":54},{"cluster_no":3,"count":60},{"cluster_no":4,"count":90},{"cluster_no":-1,"count":205}]},{"dimension":15,"min_samples":"3","min_cluster_size":"14","epsilon":"0.0","total_clusters":9,"outliers":218,"Silhouette_score":0.6298036379,"cluster_results":[{"cluster_no":7,"count":14},{"cluster_no":6,"count":18},{"cluster_no":5,"count":31},{"cluster_no":1,"count":46},{"cluster_no":0,"count":53},{"cluster_no":4,"count":54},{"cluster_no":2,"count":60},{"cluster_no":3,"count":90},{"cluster_no":-1,"count":218}]},{"dimension":15,"min_samples":"3","min_cluster_size":"15","epsilon":"0.0","total_clusters":8,"outliers":201,"Silhouette_score":0.6268275488,"cluster_results":[{"cluster_no":6,"count":31},{"cluster_no":1,"count":46},{"cluster_no":4,"count":49},{"cluster_no":0,"count":53},{"cluster_no":5,"count":54},{"cluster_no":2,"count":60},{"cluster_no":3,"count":90},{"cluster_no":-1,"count":201}]},{"dimension":15,"min_samples":"4","min_cluster_size":"5","epsilon":"0.0","total_clusters":18,"outliers":256,"Silhouette_score":0.6346305673,"cluster_results":[{"cluster_no":2,"count":5},{"cluster_no":6,"count":5},{"cluster_no":1,"count":6},{"cluster_no":5,"count":7},{"cluster_no":10,"count":7},{"cluster_no":14,"count":7},{"cluster_no":16,"count":9},{"cluster_no":0,"count":12},{"cluster_no":7,"count":14},{"cluster_no":4,"count":16},{"cluster_no":9,"count":17},{"cluster_no":11,"count":18},{"cluster_no":13,"count":19},{"cluster_no":12,"count":20},{"cluster_no":15,"count":28},{"cluster_no":3,"count":43},{"cluster_no":8,"count":95},{"cluster_no":-1,"count":256}]},{"dimension":15,"min_samples":"4","min_cluster_size":"6","epsilon":"0.0","total_clusters":14,"outliers":214,"Silhouette_score":0.6236110027,"cluster_results":[{"cluster_no":1,"count":6},{"cluster_no":8,"count":7},{"cluster_no":12,"count":7},{"cluster_no":0,"count":12},{"cluster_no":4,"count":14},{"cluster_no":7,"count":17},{"cluster_no":9,"count":18},{"cluster_no":11,"count":19},{"cluster_no":10,"count":20},{"cluster_no":3,"count":50},{"cluster_no":2,"count":52},{"cluster_no":6,"count":53},{"cluster_no":5,"count":95},{"cluster_no":-1,"count":214}]},{"dimension":15,"min_samples":"4","min_cluster_size":"7","epsilon":"0.0","total_clusters":12,"outliers":206,"Silhouette_score":0.6203283756,"cluster_results":[{"cluster_no":8,"count":7},{"cluster_no":10,"count":7},{"cluster_no":0,"count":12},{"cluster_no":3,"count":14},{"cluster_no":7,"count":17},{"cluster_no":9,"count":19},{"cluster_no":2,"count":50},{"cluster_no":1,"count":52},{"cluster_no":4,"count":52},{"cluster_no":6,"count":53},{"cluster_no":5,"count":95},{"cluster_no":-1,"count":206}]},{"dimension":15,"min_samples":"4","min_cluster_size":"8","epsilon":"0.0","total_clusters":10,"outliers":201,"Silhouette_score":0.6274307184,"cluster_results":[{"cluster_no":0,"count":12},{"cluster_no":3,"count":14},{"cluster_no":6,"count":26},{"cluster_no":8,"count":29},{"cluster_no":2,"count":50},{"cluster_no":1,"count":52},{"cluster_no":4,"count":52},{"cluster_no":7,"count":53},{"cluster_no":5,"count":95},{"cluster_no":-1,"count":201}]},{"dimension":15,"min_samples":"4","min_cluster_size":"9","epsilon":"0.0","total_clusters":10,"outliers":201,"Silhouette_score":0.6274307184,"cluster_results":[{"cluster_no":0,"count":12},{"cluster_no":3,"count":14},{"cluster_no":6,"count":26},{"cluster_no":8,"count":29},{"cluster_no":2,"count":50},{"cluster_no":1,"count":52},{"cluster_no":4,"count":52},{"cluster_no":7,"count":53},{"cluster_no":5,"count":95},{"cluster_no":-1,"count":201}]},{"dimension":15,"min_samples":"4","min_cluster_size":"10","epsilon":"0.0","total_clusters":10,"outliers":201,"Silhouette_score":0.6274307184,"cluster_results":[{"cluster_no":0,"count":12},{"cluster_no":3,"count":14},{"cluster_no":6,"count":26},{"cluster_no":8,"count":29},{"cluster_no":2,"count":50},{"cluster_no":1,"count":52},{"cluster_no":4,"count":52},{"cluster_no":7,"count":53},{"cluster_no":5,"count":95},{"cluster_no":-1,"count":201}]},{"dimension":15,"min_samples":"4","min_cluster_size":"11","epsilon":"0.0","total_clusters":10,"outliers":201,"Silhouette_score":0.6274307184,"cluster_results":[{"cluster_no":0,"count":12},{"cluster_no":3,"count":14},{"cluster_no":6,"count":26},{"cluster_no":8,"count":29},{"cluster_no":2,"count":50},{"cluster_no":1,"count":52},{"cluster_no":4,"count":52},{"cluster_no":7,"count":53},{"cluster_no":5,"count":95},{"cluster_no":-1,"count":201}]},{"dimension":15,"min_samples":"4","min_cluster_size":"12","epsilon":"0.0","total_clusters":10,"outliers":201,"Silhouette_score":0.6274307184,"cluster_results":[{"cluster_no":0,"count":12},{"cluster_no":3,"count":14},{"cluster_no":6,"count":26},{"cluster_no":8,"count":29},{"cluster_no":2,"count":50},{"cluster_no":1,"count":52},{"cluster_no":4,"count":52},{"cluster_no":7,"count":53},{"cluster_no":5,"count":95},{"cluster_no":-1,"count":201}]},{"dimension":15,"min_samples":"4","min_cluster_size":"13","epsilon":"0.0","total_clusters":9,"outliers":213,"Silhouette_score":0.6431255557,"cluster_results":[{"cluster_no":2,"count":14},{"cluster_no":5,"count":26},{"cluster_no":7,"count":29},{"cluster_no":1,"count":50},{"cluster_no":0,"count":52},{"cluster_no":3,"count":52},{"cluster_no":6,"count":53},{"cluster_no":4,"count":95},{"cluster_no":-1,"count":213}]},{"dimension":15,"min_samples":"4","min_cluster_size":"14","epsilon":"0.0","total_clusters":9,"outliers":213,"Silhouette_score":0.6431255557,"cluster_results":[{"cluster_no":2,"count":14},{"cluster_no":5,"count":26},{"cluster_no":7,"count":29},{"cluster_no":1,"count":50},{"cluster_no":0,"count":52},{"cluster_no":3,"count":52},{"cluster_no":6,"count":53},{"cluster_no":4,"count":95},{"cluster_no":-1,"count":213}]},{"dimension":15,"min_samples":"4","min_cluster_size":"15","epsilon":"0.0","total_clusters":8,"outliers":227,"Silhouette_score":0.6824178629,"cluster_results":[{"cluster_no":4,"count":26},{"cluster_no":6,"count":29},{"cluster_no":1,"count":50},{"cluster_no":0,"count":52},{"cluster_no":2,"count":52},{"cluster_no":5,"count":53},{"cluster_no":3,"count":95},{"cluster_no":-1,"count":227}]},{"dimension":15,"min_samples":"5","min_cluster_size":"5","epsilon":"0.0","total_clusters":14,"outliers":226,"Silhouette_score":0.598810153,"cluster_results":[{"cluster_no":3,"count":5},{"cluster_no":10,"count":6},{"cluster_no":6,"count":7},{"cluster_no":0,"count":11},{"cluster_no":8,"count":14},{"cluster_no":12,"count":14},{"cluster_no":9,"count":17},{"cluster_no":2,"count":20},{"cluster_no":7,"count":20},{"cluster_no":11,"count":30},{"cluster_no":1,"count":49},{"cluster_no":4,"count":55},{"cluster_no":5,"count":110},{"cluster_no":-1,"count":226}]},{"dimension":15,"min_samples":"5","min_cluster_size":"6","epsilon":"0.0","total_clusters":13,"outliers":199,"Silhouette_score":0.5994264502,"cluster_results":[{"cluster_no":9,"count":6},{"cluster_no":5,"count":7},{"cluster_no":0,"count":11},{"cluster_no":7,"count":14},{"cluster_no":11,"count":14},{"cluster_no":8,"count":17},{"cluster_no":6,"count":20},{"cluster_no":10,"count":30},{"cluster_no":2,"count":49},{"cluster_no":1,"count":52},{"cluster_no":3,"count":55},{"cluster_no":4,"count":110},{"cluster_no":-1,"count":199}]},{"dimension":15,"min_samples":"5","min_cluster_size":"7","epsilon":"0.0","total_clusters":12,"outliers":195,"Silhouette_score":0.587659454,"cluster_results":[{"cluster_no":5,"count":7},{"cluster_no":0,"count":11},{"cluster_no":7,"count":14},{"cluster_no":10,"count":14},{"cluster_no":6,"count":20},{"cluster_no":8,"count":27},{"cluster_no":9,"count":30},{"cluster_no":2,"count":49},{"cluster_no":1,"count":52},{"cluster_no":3,"count":55},{"cluster_no":4,"count":110},{"cluster_no":-1,"count":195}]},{"dimension":15,"min_samples":"5","min_cluster_size":"8","epsilon":"0.0","total_clusters":11,"outliers":202,"Silhouette_score":0.6004207781,"cluster_results":[{"cluster_no":0,"count":11},{"cluster_no":6,"count":14},{"cluster_no":9,"count":14},{"cluster_no":5,"count":20},{"cluster_no":7,"count":27},{"cluster_no":8,"count":30},{"cluster_no":2,"count":49},{"cluster_no":1,"count":52},{"cluster_no":3,"count":55},{"cluster_no":4,"count":110},{"cluster_no":-1,"count":202}]},{"dimension":15,"min_samples":"5","min_cluster_size":"9","epsilon":"0.0","total_clusters":11,"outliers":202,"Silhouette_score":0.6004207781,"cluster_results":[{"cluster_no":0,"count":11},{"cluster_no":6,"count":14},{"cluster_no":9,"count":14},{"cluster_no":5,"count":20},{"cluster_no":7,"count":27},{"cluster_no":8,"count":30},{"cluster_no":2,"count":49},{"cluster_no":1,"count":52},{"cluster_no":3,"count":55},{"cluster_no":4,"count":110},{"cluster_no":-1,"count":202}]},{"dimension":15,"min_samples":"5","min_cluster_size":"10","epsilon":"0.0","total_clusters":11,"outliers":202,"Silhouette_score":0.6004207781,"cluster_results":[{"cluster_no":0,"count":11},{"cluster_no":6,"count":14},{"cluster_no":9,"count":14},{"cluster_no":5,"count":20},{"cluster_no":7,"count":27},{"cluster_no":8,"count":30},{"cluster_no":2,"count":49},{"cluster_no":1,"count":52},{"cluster_no":3,"count":55},{"cluster_no":4,"count":110},{"cluster_no":-1,"count":202}]},{"dimension":15,"min_samples":"5","min_cluster_size":"11","epsilon":"0.0","total_clusters":11,"outliers":202,"Silhouette_score":0.6004207781,"cluster_results":[{"cluster_no":0,"count":11},{"cluster_no":6,"count":14},{"cluster_no":9,"count":14},{"cluster_no":5,"count":20},{"cluster_no":7,"count":27},{"cluster_no":8,"count":30},{"cluster_no":2,"count":49},{"cluster_no":1,"count":52},{"cluster_no":3,"count":55},{"cluster_no":4,"count":110},{"cluster_no":-1,"count":202}]},{"dimension":15,"min_samples":"5","min_cluster_size":"12","epsilon":"0.0","total_clusters":10,"outliers":213,"Silhouette_score":0.6101870971,"cluster_results":[{"cluster_no":5,"count":14},{"cluster_no":8,"count":14},{"cluster_no":4,"count":20},{"cluster_no":6,"count":27},{"cluster_no":7,"count":30},{"cluster_no":1,"count":49},{"cluster_no":0,"count":52},{"cluster_no":2,"count":55},{"cluster_no":3,"count":110},{"cluster_no":-1,"count":213}]},{"dimension":15,"min_samples":"5","min_cluster_size":"13","epsilon":"0.0","total_clusters":10,"outliers":213,"Silhouette_score":0.6101870971,"cluster_results":[{"cluster_no":5,"count":14},{"cluster_no":8,"count":14},{"cluster_no":4,"count":20},{"cluster_no":6,"count":27},{"cluster_no":7,"count":30},{"cluster_no":1,"count":49},{"cluster_no":0,"count":52},{"cluster_no":2,"count":55},{"cluster_no":3,"count":110},{"cluster_no":-1,"count":213}]},{"dimension":15,"min_samples":"5","min_cluster_size":"14","epsilon":"0.0","total_clusters":10,"outliers":213,"Silhouette_score":0.6101870971,"cluster_results":[{"cluster_no":5,"count":14},{"cluster_no":8,"count":14},{"cluster_no":4,"count":20},{"cluster_no":6,"count":27},{"cluster_no":7,"count":30},{"cluster_no":1,"count":49},{"cluster_no":0,"count":52},{"cluster_no":2,"count":55},{"cluster_no":3,"count":110},{"cluster_no":-1,"count":213}]},{"dimension":15,"min_samples":"5","min_cluster_size":"15","epsilon":"0.0","total_clusters":8,"outliers":206,"Silhouette_score":0.6680121594,"cluster_results":[{"cluster_no":6,"count":27},{"cluster_no":4,"count":34},{"cluster_no":1,"count":49},{"cluster_no":5,"count":51},{"cluster_no":0,"count":52},{"cluster_no":2,"count":55},{"cluster_no":3,"count":110},{"cluster_no":-1,"count":206}]},{"dimension":15,"min_samples":"6","min_cluster_size":"5","epsilon":"0.0","total_clusters":12,"outliers":213,"Silhouette_score":0.6347993108,"cluster_results":[{"cluster_no":5,"count":5},{"cluster_no":10,"count":5},{"cluster_no":0,"count":11},{"cluster_no":7,"count":13},{"cluster_no":9,"count":18},{"cluster_no":6,"count":21},{"cluster_no":2,"count":45},{"cluster_no":1,"count":51},{"cluster_no":3,"count":52},{"cluster_no":8,"count":53},{"cluster_no":4,"count":97},{"cluster_no":-1,"count":213}]},{"dimension":15,"min_samples":"6","min_cluster_size":"6","epsilon":"0.0","total_clusters":10,"outliers":212,"Silhouette_score":0.6603551164,"cluster_results":[{"cluster_no":0,"count":11},{"cluster_no":6,"count":13},{"cluster_no":5,"count":21},{"cluster_no":8,"count":29},{"cluster_no":2,"count":45},{"cluster_no":1,"count":51},{"cluster_no":3,"count":52},{"cluster_no":7,"count":53},{"cluster_no":4,"count":97},{"cluster_no":-1,"count":212}]},{"dimension":15,"min_samples":"6","min_cluster_size":"7","epsilon":"0.0","total_clusters":10,"outliers":212,"Silhouette_score":0.6603551164,"cluster_results":[{"cluster_no":0,"count":11},{"cluster_no":6,"count":13},{"cluster_no":5,"count":21},{"cluster_no":8,"count":29},{"cluster_no":2,"count":45},{"cluster_no":1,"count":51},{"cluster_no":3,"count":52},{"cluster_no":7,"count":53},{"cluster_no":4,"count":97},{"cluster_no":-1,"count":212}]},{"dimension":15,"min_samples":"6","min_cluster_size":"8","epsilon":"0.0","total_clusters":10,"outliers":212,"Silhouette_score":0.6603551164,"cluster_results":[{"cluster_no":0,"count":11},{"cluster_no":6,"count":13},{"cluster_no":5,"count":21},{"cluster_no":8,"count":29},{"cluster_no":2,"count":45},{"cluster_no":1,"count":51},{"cluster_no":3,"count":52},{"cluster_no":7,"count":53},{"cluster_no":4,"count":97},{"cluster_no":-1,"count":212}]},{"dimension":15,"min_samples":"6","min_cluster_size":"9","epsilon":"0.0","total_clusters":10,"outliers":212,"Silhouette_score":0.6603551164,"cluster_results":[{"cluster_no":0,"count":11},{"cluster_no":6,"count":13},{"cluster_no":5,"count":21},{"cluster_no":8,"count":29},{"cluster_no":2,"count":45},{"cluster_no":1,"count":51},{"cluster_no":3,"count":52},{"cluster_no":7,"count":53},{"cluster_no":4,"count":97},{"cluster_no":-1,"count":212}]},{"dimension":15,"min_samples":"6","min_cluster_size":"10","epsilon":"0.0","total_clusters":10,"outliers":212,"Silhouette_score":0.6603551164,"cluster_results":[{"cluster_no":0,"count":11},{"cluster_no":6,"count":13},{"cluster_no":5,"count":21},{"cluster_no":8,"count":29},{"cluster_no":2,"count":45},{"cluster_no":1,"count":51},{"cluster_no":3,"count":52},{"cluster_no":7,"count":53},{"cluster_no":4,"count":97},{"cluster_no":-1,"count":212}]},{"dimension":15,"min_samples":"6","min_cluster_size":"11","epsilon":"0.0","total_clusters":10,"outliers":212,"Silhouette_score":0.6603551164,"cluster_results":[{"cluster_no":0,"count":11},{"cluster_no":6,"count":13},{"cluster_no":5,"count":21},{"cluster_no":8,"count":29},{"cluster_no":2,"count":45},{"cluster_no":1,"count":51},{"cluster_no":3,"count":52},{"cluster_no":7,"count":53},{"cluster_no":4,"count":97},{"cluster_no":-1,"count":212}]},{"dimension":15,"min_samples":"6","min_cluster_size":"12","epsilon":"0.0","total_clusters":9,"outliers":223,"Silhouette_score":0.6738525501,"cluster_results":[{"cluster_no":5,"count":13},{"cluster_no":4,"count":21},{"cluster_no":7,"count":29},{"cluster_no":1,"count":45},{"cluster_no":0,"count":51},{"cluster_no":2,"count":52},{"cluster_no":6,"count":53},{"cluster_no":3,"count":97},{"cluster_no":-1,"count":223}]},{"dimension":15,"min_samples":"6","min_cluster_size":"13","epsilon":"0.0","total_clusters":9,"outliers":223,"Silhouette_score":0.6738525501,"cluster_results":[{"cluster_no":5,"count":13},{"cluster_no":4,"count":21},{"cluster_no":7,"count":29},{"cluster_no":1,"count":45},{"cluster_no":0,"count":51},{"cluster_no":2,"count":52},{"cluster_no":6,"count":53},{"cluster_no":3,"count":97},{"cluster_no":-1,"count":223}]},{"dimension":15,"min_samples":"6","min_cluster_size":"14","epsilon":"0.0","total_clusters":8,"outliers":222,"Silhouette_score":0.6856388214,"cluster_results":[{"cluster_no":6,"count":29},{"cluster_no":4,"count":35},{"cluster_no":1,"count":45},{"cluster_no":0,"count":51},{"cluster_no":2,"count":52},{"cluster_no":5,"count":53},{"cluster_no":3,"count":97},{"cluster_no":-1,"count":222}]},{"dimension":15,"min_samples":"6","min_cluster_size":"15","epsilon":"0.0","total_clusters":8,"outliers":222,"Silhouette_score":0.6856388214,"cluster_results":[{"cluster_no":6,"count":29},{"cluster_no":4,"count":35},{"cluster_no":1,"count":45},{"cluster_no":0,"count":51},{"cluster_no":2,"count":52},{"cluster_no":5,"count":53},{"cluster_no":3,"count":97},{"cluster_no":-1,"count":222}]},{"dimension":15,"min_samples":"7","min_cluster_size":"5","epsilon":"0.0","total_clusters":10,"outliers":236,"Silhouette_score":0.6741225394,"cluster_results":[{"cluster_no":2,"count":11},{"cluster_no":3,"count":13},{"cluster_no":6,"count":22},{"cluster_no":8,"count":27},{"cluster_no":1,"count":41},{"cluster_no":0,"count":46},{"cluster_no":4,"count":49},{"cluster_no":7,"count":53},{"cluster_no":5,"count":86},{"cluster_no":-1,"count":236}]},{"dimension":15,"min_samples":"7","min_cluster_size":"6","epsilon":"0.0","total_clusters":10,"outliers":236,"Silhouette_score":0.6741225394,"cluster_results":[{"cluster_no":2,"count":11},{"cluster_no":3,"count":13},{"cluster_no":6,"count":22},{"cluster_no":8,"count":27},{"cluster_no":1,"count":41},{"cluster_no":0,"count":46},{"cluster_no":4,"count":49},{"cluster_no":7,"count":53},{"cluster_no":5,"count":86},{"cluster_no":-1,"count":236}]},{"dimension":15,"min_samples":"7","min_cluster_size":"7","epsilon":"0.0","total_clusters":10,"outliers":236,"Silhouette_score":0.6741225394,"cluster_results":[{"cluster_no":2,"count":11},{"cluster_no":3,"count":13},{"cluster_no":6,"count":22},{"cluster_no":8,"count":27},{"cluster_no":1,"count":41},{"cluster_no":0,"count":46},{"cluster_no":4,"count":49},{"cluster_no":7,"count":53},{"cluster_no":5,"count":86},{"cluster_no":-1,"count":236}]},{"dimension":15,"min_samples":"7","min_cluster_size":"8","epsilon":"0.0","total_clusters":10,"outliers":236,"Silhouette_score":0.6741225394,"cluster_results":[{"cluster_no":2,"count":11},{"cluster_no":3,"count":13},{"cluster_no":6,"count":22},{"cluster_no":8,"count":27},{"cluster_no":1,"count":41},{"cluster_no":0,"count":46},{"cluster_no":4,"count":49},{"cluster_no":7,"count":53},{"cluster_no":5,"count":86},{"cluster_no":-1,"count":236}]},{"dimension":15,"min_samples":"7","min_cluster_size":"9","epsilon":"0.0","total_clusters":10,"outliers":236,"Silhouette_score":0.6741225394,"cluster_results":[{"cluster_no":2,"count":11},{"cluster_no":3,"count":13},{"cluster_no":6,"count":22},{"cluster_no":8,"count":27},{"cluster_no":1,"count":41},{"cluster_no":0,"count":46},{"cluster_no":4,"count":49},{"cluster_no":7,"count":53},{"cluster_no":5,"count":86},{"cluster_no":-1,"count":236}]},{"dimension":15,"min_samples":"7","min_cluster_size":"10","epsilon":"0.0","total_clusters":10,"outliers":236,"Silhouette_score":0.6741225394,"cluster_results":[{"cluster_no":2,"count":11},{"cluster_no":3,"count":13},{"cluster_no":6,"count":22},{"cluster_no":8,"count":27},{"cluster_no":1,"count":41},{"cluster_no":0,"count":46},{"cluster_no":4,"count":49},{"cluster_no":7,"count":53},{"cluster_no":5,"count":86},{"cluster_no":-1,"count":236}]},{"dimension":15,"min_samples":"7","min_cluster_size":"11","epsilon":"0.0","total_clusters":10,"outliers":236,"Silhouette_score":0.6741225394,"cluster_results":[{"cluster_no":2,"count":11},{"cluster_no":3,"count":13},{"cluster_no":6,"count":22},{"cluster_no":8,"count":27},{"cluster_no":1,"count":41},{"cluster_no":0,"count":46},{"cluster_no":4,"count":49},{"cluster_no":7,"count":53},{"cluster_no":5,"count":86},{"cluster_no":-1,"count":236}]},{"dimension":15,"min_samples":"7","min_cluster_size":"12","epsilon":"0.0","total_clusters":9,"outliers":247,"Silhouette_score":0.6868815699,"cluster_results":[{"cluster_no":2,"count":13},{"cluster_no":5,"count":22},{"cluster_no":7,"count":27},{"cluster_no":1,"count":41},{"cluster_no":0,"count":46},{"cluster_no":3,"count":49},{"cluster_no":6,"count":53},{"cluster_no":4,"count":86},{"cluster_no":-1,"count":247}]},{"dimension":15,"min_samples":"7","min_cluster_size":"13","epsilon":"0.0","total_clusters":9,"outliers":247,"Silhouette_score":0.6868815699,"cluster_results":[{"cluster_no":2,"count":13},{"cluster_no":5,"count":22},{"cluster_no":7,"count":27},{"cluster_no":1,"count":41},{"cluster_no":0,"count":46},{"cluster_no":3,"count":49},{"cluster_no":6,"count":53},{"cluster_no":4,"count":86},{"cluster_no":-1,"count":247}]},{"dimension":15,"min_samples":"7","min_cluster_size":"14","epsilon":"0.0","total_clusters":8,"outliers":260,"Silhouette_score":0.7352103378,"cluster_results":[{"cluster_no":4,"count":22},{"cluster_no":6,"count":27},{"cluster_no":1,"count":41},{"cluster_no":0,"count":46},{"cluster_no":2,"count":49},{"cluster_no":5,"count":53},{"cluster_no":3,"count":86},{"cluster_no":-1,"count":260}]},{"dimension":15,"min_samples":"7","min_cluster_size":"15","epsilon":"0.0","total_clusters":8,"outliers":260,"Silhouette_score":0.7352103378,"cluster_results":[{"cluster_no":4,"count":22},{"cluster_no":6,"count":27},{"cluster_no":1,"count":41},{"cluster_no":0,"count":46},{"cluster_no":2,"count":49},{"cluster_no":5,"count":53},{"cluster_no":3,"count":86},{"cluster_no":-1,"count":260}]},{"dimension":15,"min_samples":"8","min_cluster_size":"5","epsilon":"0.0","total_clusters":10,"outliers":264,"Silhouette_score":0.6997331599,"cluster_results":[{"cluster_no":3,"count":11},{"cluster_no":2,"count":12},{"cluster_no":4,"count":21},{"cluster_no":6,"count":29},{"cluster_no":1,"count":39},{"cluster_no":0,"count":46},{"cluster_no":7,"count":46},{"cluster_no":5,"count":50},{"cluster_no":8,"count":66},{"cluster_no":-1,"count":264}]},{"dimension":15,"min_samples":"8","min_cluster_size":"6","epsilon":"0.0","total_clusters":10,"outliers":264,"Silhouette_score":0.6997331599,"cluster_results":[{"cluster_no":3,"count":11},{"cluster_no":2,"count":12},{"cluster_no":4,"count":21},{"cluster_no":6,"count":29},{"cluster_no":1,"count":39},{"cluster_no":0,"count":46},{"cluster_no":7,"count":46},{"cluster_no":5,"count":50},{"cluster_no":8,"count":66},{"cluster_no":-1,"count":264}]},{"dimension":15,"min_samples":"8","min_cluster_size":"7","epsilon":"0.0","total_clusters":10,"outliers":264,"Silhouette_score":0.6997331599,"cluster_results":[{"cluster_no":3,"count":11},{"cluster_no":2,"count":12},{"cluster_no":4,"count":21},{"cluster_no":6,"count":29},{"cluster_no":1,"count":39},{"cluster_no":0,"count":46},{"cluster_no":7,"count":46},{"cluster_no":5,"count":50},{"cluster_no":8,"count":66},{"cluster_no":-1,"count":264}]},{"dimension":15,"min_samples":"8","min_cluster_size":"8","epsilon":"0.0","total_clusters":10,"outliers":264,"Silhouette_score":0.6997331599,"cluster_results":[{"cluster_no":3,"count":11},{"cluster_no":2,"count":12},{"cluster_no":4,"count":21},{"cluster_no":6,"count":29},{"cluster_no":1,"count":39},{"cluster_no":0,"count":46},{"cluster_no":7,"count":46},{"cluster_no":5,"count":50},{"cluster_no":8,"count":66},{"cluster_no":-1,"count":264}]},{"dimension":15,"min_samples":"8","min_cluster_size":"9","epsilon":"0.0","total_clusters":10,"outliers":264,"Silhouette_score":0.6997331599,"cluster_results":[{"cluster_no":3,"count":11},{"cluster_no":2,"count":12},{"cluster_no":4,"count":21},{"cluster_no":6,"count":29},{"cluster_no":1,"count":39},{"cluster_no":0,"count":46},{"cluster_no":7,"count":46},{"cluster_no":5,"count":50},{"cluster_no":8,"count":66},{"cluster_no":-1,"count":264}]},{"dimension":15,"min_samples":"8","min_cluster_size":"10","epsilon":"0.0","total_clusters":10,"outliers":264,"Silhouette_score":0.6997331599,"cluster_results":[{"cluster_no":3,"count":11},{"cluster_no":2,"count":12},{"cluster_no":4,"count":21},{"cluster_no":6,"count":29},{"cluster_no":1,"count":39},{"cluster_no":0,"count":46},{"cluster_no":7,"count":46},{"cluster_no":5,"count":50},{"cluster_no":8,"count":66},{"cluster_no":-1,"count":264}]},{"dimension":15,"min_samples":"8","min_cluster_size":"11","epsilon":"0.0","total_clusters":10,"outliers":264,"Silhouette_score":0.6997331599,"cluster_results":[{"cluster_no":3,"count":11},{"cluster_no":2,"count":12},{"cluster_no":4,"count":21},{"cluster_no":6,"count":29},{"cluster_no":1,"count":39},{"cluster_no":0,"count":46},{"cluster_no":7,"count":46},{"cluster_no":5,"count":50},{"cluster_no":8,"count":66},{"cluster_no":-1,"count":264}]},{"dimension":15,"min_samples":"8","min_cluster_size":"12","epsilon":"0.0","total_clusters":9,"outliers":275,"Silhouette_score":0.7479706536,"cluster_results":[{"cluster_no":2,"count":12},{"cluster_no":3,"count":21},{"cluster_no":5,"count":29},{"cluster_no":1,"count":39},{"cluster_no":0,"count":46},{"cluster_no":6,"count":46},{"cluster_no":4,"count":50},{"cluster_no":7,"count":66},{"cluster_no":-1,"count":275}]},{"dimension":15,"min_samples":"8","min_cluster_size":"13","epsilon":"0.0","total_clusters":8,"outliers":287,"Silhouette_score":0.7735745931,"cluster_results":[{"cluster_no":2,"count":21},{"cluster_no":4,"count":29},{"cluster_no":1,"count":39},{"cluster_no":0,"count":46},{"cluster_no":5,"count":46},{"cluster_no":3,"count":50},{"cluster_no":6,"count":66},{"cluster_no":-1,"count":287}]},{"dimension":15,"min_samples":"8","min_cluster_size":"14","epsilon":"0.0","total_clusters":8,"outliers":287,"Silhouette_score":0.7735745931,"cluster_results":[{"cluster_no":2,"count":21},{"cluster_no":4,"count":29},{"cluster_no":1,"count":39},{"cluster_no":0,"count":46},{"cluster_no":5,"count":46},{"cluster_no":3,"count":50},{"cluster_no":6,"count":66},{"cluster_no":-1,"count":287}]},{"dimension":15,"min_samples":"8","min_cluster_size":"15","epsilon":"0.0","total_clusters":8,"outliers":287,"Silhouette_score":0.7735745931,"cluster_results":[{"cluster_no":2,"count":21},{"cluster_no":4,"count":29},{"cluster_no":1,"count":39},{"cluster_no":0,"count":46},{"cluster_no":5,"count":46},{"cluster_no":3,"count":50},{"cluster_no":6,"count":66},{"cluster_no":-1,"count":287}]},{"dimension":15,"min_samples":"9","min_cluster_size":"5","epsilon":"0.0","total_clusters":10,"outliers":271,"Silhouette_score":0.7050912629,"cluster_results":[{"cluster_no":2,"count":10},{"cluster_no":3,"count":11},{"cluster_no":4,"count":23},{"cluster_no":6,"count":28},{"cluster_no":1,"count":38},{"cluster_no":7,"count":45},{"cluster_no":0,"count":46},{"cluster_no":5,"count":51},{"cluster_no":8,"count":61},{"cluster_no":-1,"count":271}]},{"dimension":15,"min_samples":"9","min_cluster_size":"6","epsilon":"0.0","total_clusters":10,"outliers":271,"Silhouette_score":0.7050912629,"cluster_results":[{"cluster_no":2,"count":10},{"cluster_no":3,"count":11},{"cluster_no":4,"count":23},{"cluster_no":6,"count":28},{"cluster_no":1,"count":38},{"cluster_no":7,"count":45},{"cluster_no":0,"count":46},{"cluster_no":5,"count":51},{"cluster_no":8,"count":61},{"cluster_no":-1,"count":271}]},{"dimension":15,"min_samples":"9","min_cluster_size":"7","epsilon":"0.0","total_clusters":10,"outliers":271,"Silhouette_score":0.7050912629,"cluster_results":[{"cluster_no":2,"count":10},{"cluster_no":3,"count":11},{"cluster_no":4,"count":23},{"cluster_no":6,"count":28},{"cluster_no":1,"count":38},{"cluster_no":7,"count":45},{"cluster_no":0,"count":46},{"cluster_no":5,"count":51},{"cluster_no":8,"count":61},{"cluster_no":-1,"count":271}]},{"dimension":15,"min_samples":"9","min_cluster_size":"8","epsilon":"0.0","total_clusters":10,"outliers":271,"Silhouette_score":0.7050912629,"cluster_results":[{"cluster_no":2,"count":10},{"cluster_no":3,"count":11},{"cluster_no":4,"count":23},{"cluster_no":6,"count":28},{"cluster_no":1,"count":38},{"cluster_no":7,"count":45},{"cluster_no":0,"count":46},{"cluster_no":5,"count":51},{"cluster_no":8,"count":61},{"cluster_no":-1,"count":271}]},{"dimension":15,"min_samples":"9","min_cluster_size":"9","epsilon":"0.0","total_clusters":10,"outliers":271,"Silhouette_score":0.7050912629,"cluster_results":[{"cluster_no":2,"count":10},{"cluster_no":3,"count":11},{"cluster_no":4,"count":23},{"cluster_no":6,"count":28},{"cluster_no":1,"count":38},{"cluster_no":7,"count":45},{"cluster_no":0,"count":46},{"cluster_no":5,"count":51},{"cluster_no":8,"count":61},{"cluster_no":-1,"count":271}]},{"dimension":15,"min_samples":"9","min_cluster_size":"10","epsilon":"0.0","total_clusters":10,"outliers":271,"Silhouette_score":0.7050912629,"cluster_results":[{"cluster_no":2,"count":10},{"cluster_no":3,"count":11},{"cluster_no":4,"count":23},{"cluster_no":6,"count":28},{"cluster_no":1,"count":38},{"cluster_no":7,"count":45},{"cluster_no":0,"count":46},{"cluster_no":5,"count":51},{"cluster_no":8,"count":61},{"cluster_no":-1,"count":271}]},{"dimension":15,"min_samples":"9","min_cluster_size":"11","epsilon":"0.0","total_clusters":9,"outliers":281,"Silhouette_score":0.7222453878,"cluster_results":[{"cluster_no":2,"count":11},{"cluster_no":3,"count":23},{"cluster_no":5,"count":28},{"cluster_no":1,"count":38},{"cluster_no":6,"count":45},{"cluster_no":0,"count":46},{"cluster_no":4,"count":51},{"cluster_no":7,"count":61},{"cluster_no":-1,"count":281}]},{"dimension":15,"min_samples":"9","min_cluster_size":"12","epsilon":"0.0","total_clusters":8,"outliers":292,"Silhouette_score":0.773826348,"cluster_results":[{"cluster_no":2,"count":23},{"cluster_no":4,"count":28},{"cluster_no":1,"count":38},{"cluster_no":5,"count":45},{"cluster_no":0,"count":46},{"cluster_no":3,"count":51},{"cluster_no":6,"count":61},{"cluster_no":-1,"count":292}]},{"dimension":15,"min_samples":"9","min_cluster_size":"13","epsilon":"0.0","total_clusters":8,"outliers":292,"Silhouette_score":0.773826348,"cluster_results":[{"cluster_no":2,"count":23},{"cluster_no":4,"count":28},{"cluster_no":1,"count":38},{"cluster_no":5,"count":45},{"cluster_no":0,"count":46},{"cluster_no":3,"count":51},{"cluster_no":6,"count":61},{"cluster_no":-1,"count":292}]},{"dimension":15,"min_samples":"9","min_cluster_size":"14","epsilon":"0.0","total_clusters":8,"outliers":292,"Silhouette_score":0.773826348,"cluster_results":[{"cluster_no":2,"count":23},{"cluster_no":4,"count":28},{"cluster_no":1,"count":38},{"cluster_no":5,"count":45},{"cluster_no":0,"count":46},{"cluster_no":3,"count":51},{"cluster_no":6,"count":61},{"cluster_no":-1,"count":292}]},{"dimension":15,"min_samples":"9","min_cluster_size":"15","epsilon":"0.0","total_clusters":8,"outliers":292,"Silhouette_score":0.773826348,"cluster_results":[{"cluster_no":2,"count":23},{"cluster_no":4,"count":28},{"cluster_no":1,"count":38},{"cluster_no":5,"count":45},{"cluster_no":0,"count":46},{"cluster_no":3,"count":51},{"cluster_no":6,"count":61},{"cluster_no":-1,"count":292}]},{"dimension":15,"min_samples":"10","min_cluster_size":"5","epsilon":"0.0","total_clusters":10,"outliers":277,"Silhouette_score":0.7189145057,"cluster_results":[{"cluster_no":2,"count":11},{"cluster_no":4,"count":11},{"cluster_no":3,"count":22},{"cluster_no":6,"count":30},{"cluster_no":1,"count":37},{"cluster_no":7,"count":43},{"cluster_no":0,"count":45},{"cluster_no":5,"count":48},{"cluster_no":8,"count":60},{"cluster_no":-1,"count":277}]},{"dimension":15,"min_samples":"10","min_cluster_size":"6","epsilon":"0.0","total_clusters":10,"outliers":277,"Silhouette_score":0.7189145057,"cluster_results":[{"cluster_no":2,"count":11},{"cluster_no":4,"count":11},{"cluster_no":3,"count":22},{"cluster_no":6,"count":30},{"cluster_no":1,"count":37},{"cluster_no":7,"count":43},{"cluster_no":0,"count":45},{"cluster_no":5,"count":48},{"cluster_no":8,"count":60},{"cluster_no":-1,"count":277}]},{"dimension":15,"min_samples":"10","min_cluster_size":"7","epsilon":"0.0","total_clusters":10,"outliers":277,"Silhouette_score":0.7189145057,"cluster_results":[{"cluster_no":2,"count":11},{"cluster_no":4,"count":11},{"cluster_no":3,"count":22},{"cluster_no":6,"count":30},{"cluster_no":1,"count":37},{"cluster_no":7,"count":43},{"cluster_no":0,"count":45},{"cluster_no":5,"count":48},{"cluster_no":8,"count":60},{"cluster_no":-1,"count":277}]},{"dimension":15,"min_samples":"10","min_cluster_size":"8","epsilon":"0.0","total_clusters":10,"outliers":277,"Silhouette_score":0.7189145057,"cluster_results":[{"cluster_no":2,"count":11},{"cluster_no":4,"count":11},{"cluster_no":3,"count":22},{"cluster_no":6,"count":30},{"cluster_no":1,"count":37},{"cluster_no":7,"count":43},{"cluster_no":0,"count":45},{"cluster_no":5,"count":48},{"cluster_no":8,"count":60},{"cluster_no":-1,"count":277}]},{"dimension":15,"min_samples":"10","min_cluster_size":"9","epsilon":"0.0","total_clusters":10,"outliers":277,"Silhouette_score":0.7189145057,"cluster_results":[{"cluster_no":2,"count":11},{"cluster_no":4,"count":11},{"cluster_no":3,"count":22},{"cluster_no":6,"count":30},{"cluster_no":1,"count":37},{"cluster_no":7,"count":43},{"cluster_no":0,"count":45},{"cluster_no":5,"count":48},{"cluster_no":8,"count":60},{"cluster_no":-1,"count":277}]},{"dimension":15,"min_samples":"10","min_cluster_size":"10","epsilon":"0.0","total_clusters":10,"outliers":277,"Silhouette_score":0.7189145057,"cluster_results":[{"cluster_no":2,"count":11},{"cluster_no":4,"count":11},{"cluster_no":3,"count":22},{"cluster_no":6,"count":30},{"cluster_no":1,"count":37},{"cluster_no":7,"count":43},{"cluster_no":0,"count":45},{"cluster_no":5,"count":48},{"cluster_no":8,"count":60},{"cluster_no":-1,"count":277}]},{"dimension":15,"min_samples":"10","min_cluster_size":"11","epsilon":"0.0","total_clusters":10,"outliers":277,"Silhouette_score":0.7189145057,"cluster_results":[{"cluster_no":2,"count":11},{"cluster_no":4,"count":11},{"cluster_no":3,"count":22},{"cluster_no":6,"count":30},{"cluster_no":1,"count":37},{"cluster_no":7,"count":43},{"cluster_no":0,"count":45},{"cluster_no":5,"count":48},{"cluster_no":8,"count":60},{"cluster_no":-1,"count":277}]},{"dimension":15,"min_samples":"10","min_cluster_size":"12","epsilon":"0.0","total_clusters":8,"outliers":299,"Silhouette_score":0.7845398855,"cluster_results":[{"cluster_no":2,"count":22},{"cluster_no":4,"count":30},{"cluster_no":1,"count":37},{"cluster_no":5,"count":43},{"cluster_no":0,"count":45},{"cluster_no":3,"count":48},{"cluster_no":6,"count":60},{"cluster_no":-1,"count":299}]},{"dimension":15,"min_samples":"10","min_cluster_size":"13","epsilon":"0.0","total_clusters":8,"outliers":299,"Silhouette_score":0.7845398855,"cluster_results":[{"cluster_no":2,"count":22},{"cluster_no":4,"count":30},{"cluster_no":1,"count":37},{"cluster_no":5,"count":43},{"cluster_no":0,"count":45},{"cluster_no":3,"count":48},{"cluster_no":6,"count":60},{"cluster_no":-1,"count":299}]},{"dimension":15,"min_samples":"10","min_cluster_size":"14","epsilon":"0.0","total_clusters":8,"outliers":299,"Silhouette_score":0.7845398855,"cluster_results":[{"cluster_no":2,"count":22},{"cluster_no":4,"count":30},{"cluster_no":1,"count":37},{"cluster_no":5,"count":43},{"cluster_no":0,"count":45},{"cluster_no":3,"count":48},{"cluster_no":6,"count":60},{"cluster_no":-1,"count":299}]},{"dimension":15,"min_samples":"10","min_cluster_size":"15","epsilon":"0.0","total_clusters":8,"outliers":299,"Silhouette_score":0.7845398855,"cluster_results":[{"cluster_no":2,"count":22},{"cluster_no":4,"count":30},{"cluster_no":1,"count":37},{"cluster_no":5,"count":43},{"cluster_no":0,"count":45},{"cluster_no":3,"count":48},{"cluster_no":6,"count":60},{"cluster_no":-1,"count":299}]},{"dimension":15,"min_samples":"11","min_cluster_size":"5","epsilon":"0.0","total_clusters":9,"outliers":299,"Silhouette_score":0.732443363,"cluster_results":[{"cluster_no":5,"count":7},{"cluster_no":2,"count":21},{"cluster_no":4,"count":30},{"cluster_no":6,"count":38},{"cluster_no":0,"count":42},{"cluster_no":1,"count":46},{"cluster_no":3,"count":49},{"cluster_no":7,"count":52},{"cluster_no":-1,"count":299}]},{"dimension":15,"min_samples":"11","min_cluster_size":"6","epsilon":"0.0","total_clusters":4,"outliers":128,"Silhouette_score":-0.1520630663,"cluster_results":[{"cluster_no":0,"count":42},{"cluster_no":2,"count":46},{"cluster_no":-1,"count":128},{"cluster_no":1,"count":368}]},{"dimension":15,"min_samples":"11","min_cluster_size":"7","epsilon":"0.0","total_clusters":4,"outliers":128,"Silhouette_score":-0.1520630663,"cluster_results":[{"cluster_no":0,"count":42},{"cluster_no":2,"count":46},{"cluster_no":-1,"count":128},{"cluster_no":1,"count":368}]},{"dimension":15,"min_samples":"11","min_cluster_size":"8","epsilon":"0.0","total_clusters":4,"outliers":128,"Silhouette_score":-0.1520630663,"cluster_results":[{"cluster_no":0,"count":42},{"cluster_no":2,"count":46},{"cluster_no":-1,"count":128},{"cluster_no":1,"count":368}]},{"dimension":15,"min_samples":"11","min_cluster_size":"9","epsilon":"0.0","total_clusters":4,"outliers":128,"Silhouette_score":-0.1520630663,"cluster_results":[{"cluster_no":0,"count":42},{"cluster_no":2,"count":46},{"cluster_no":-1,"count":128},{"cluster_no":1,"count":368}]},{"dimension":15,"min_samples":"11","min_cluster_size":"10","epsilon":"0.0","total_clusters":4,"outliers":128,"Silhouette_score":-0.1520630663,"cluster_results":[{"cluster_no":0,"count":42},{"cluster_no":2,"count":46},{"cluster_no":-1,"count":128},{"cluster_no":1,"count":368}]},{"dimension":15,"min_samples":"11","min_cluster_size":"11","epsilon":"0.0","total_clusters":4,"outliers":128,"Silhouette_score":-0.1520630663,"cluster_results":[{"cluster_no":0,"count":42},{"cluster_no":2,"count":46},{"cluster_no":-1,"count":128},{"cluster_no":1,"count":368}]},{"dimension":15,"min_samples":"11","min_cluster_size":"12","epsilon":"0.0","total_clusters":4,"outliers":128,"Silhouette_score":-0.1520630663,"cluster_results":[{"cluster_no":0,"count":42},{"cluster_no":2,"count":46},{"cluster_no":-1,"count":128},{"cluster_no":1,"count":368}]},{"dimension":15,"min_samples":"11","min_cluster_size":"13","epsilon":"0.0","total_clusters":4,"outliers":128,"Silhouette_score":-0.1520630663,"cluster_results":[{"cluster_no":0,"count":42},{"cluster_no":2,"count":46},{"cluster_no":-1,"count":128},{"cluster_no":1,"count":368}]},{"dimension":15,"min_samples":"11","min_cluster_size":"14","epsilon":"0.0","total_clusters":4,"outliers":128,"Silhouette_score":-0.1520630663,"cluster_results":[{"cluster_no":0,"count":42},{"cluster_no":2,"count":46},{"cluster_no":-1,"count":128},{"cluster_no":1,"count":368}]},{"dimension":15,"min_samples":"11","min_cluster_size":"15","epsilon":"0.0","total_clusters":4,"outliers":128,"Silhouette_score":-0.1520630663,"cluster_results":[{"cluster_no":0,"count":42},{"cluster_no":2,"count":46},{"cluster_no":-1,"count":128},{"cluster_no":1,"count":368}]},{"dimension":15,"min_samples":"12","min_cluster_size":"5","epsilon":"0.0","total_clusters":4,"outliers":140,"Silhouette_score":-0.1452589358,"cluster_results":[{"cluster_no":0,"count":41},{"cluster_no":2,"count":46},{"cluster_no":-1,"count":140},{"cluster_no":1,"count":357}]},{"dimension":15,"min_samples":"12","min_cluster_size":"6","epsilon":"0.0","total_clusters":4,"outliers":140,"Silhouette_score":-0.1452589358,"cluster_results":[{"cluster_no":0,"count":41},{"cluster_no":2,"count":46},{"cluster_no":-1,"count":140},{"cluster_no":1,"count":357}]},{"dimension":15,"min_samples":"12","min_cluster_size":"7","epsilon":"0.0","total_clusters":4,"outliers":140,"Silhouette_score":-0.1452589358,"cluster_results":[{"cluster_no":0,"count":41},{"cluster_no":2,"count":46},{"cluster_no":-1,"count":140},{"cluster_no":1,"count":357}]},{"dimension":15,"min_samples":"12","min_cluster_size":"8","epsilon":"0.0","total_clusters":4,"outliers":140,"Silhouette_score":-0.1452589358,"cluster_results":[{"cluster_no":0,"count":41},{"cluster_no":2,"count":46},{"cluster_no":-1,"count":140},{"cluster_no":1,"count":357}]},{"dimension":15,"min_samples":"12","min_cluster_size":"9","epsilon":"0.0","total_clusters":4,"outliers":140,"Silhouette_score":-0.1452589358,"cluster_results":[{"cluster_no":0,"count":41},{"cluster_no":2,"count":46},{"cluster_no":-1,"count":140},{"cluster_no":1,"count":357}]},{"dimension":15,"min_samples":"12","min_cluster_size":"10","epsilon":"0.0","total_clusters":4,"outliers":140,"Silhouette_score":-0.1452589358,"cluster_results":[{"cluster_no":0,"count":41},{"cluster_no":2,"count":46},{"cluster_no":-1,"count":140},{"cluster_no":1,"count":357}]},{"dimension":15,"min_samples":"12","min_cluster_size":"11","epsilon":"0.0","total_clusters":4,"outliers":140,"Silhouette_score":-0.1452589358,"cluster_results":[{"cluster_no":0,"count":41},{"cluster_no":2,"count":46},{"cluster_no":-1,"count":140},{"cluster_no":1,"count":357}]},{"dimension":15,"min_samples":"12","min_cluster_size":"12","epsilon":"0.0","total_clusters":4,"outliers":140,"Silhouette_score":-0.1452589358,"cluster_results":[{"cluster_no":0,"count":41},{"cluster_no":2,"count":46},{"cluster_no":-1,"count":140},{"cluster_no":1,"count":357}]},{"dimension":15,"min_samples":"12","min_cluster_size":"13","epsilon":"0.0","total_clusters":4,"outliers":140,"Silhouette_score":-0.1452589358,"cluster_results":[{"cluster_no":0,"count":41},{"cluster_no":2,"count":46},{"cluster_no":-1,"count":140},{"cluster_no":1,"count":357}]},{"dimension":15,"min_samples":"12","min_cluster_size":"14","epsilon":"0.0","total_clusters":4,"outliers":140,"Silhouette_score":-0.1452589358,"cluster_results":[{"cluster_no":0,"count":41},{"cluster_no":2,"count":46},{"cluster_no":-1,"count":140},{"cluster_no":1,"count":357}]},{"dimension":15,"min_samples":"12","min_cluster_size":"15","epsilon":"0.0","total_clusters":4,"outliers":140,"Silhouette_score":-0.1452589358,"cluster_results":[{"cluster_no":0,"count":41},{"cluster_no":2,"count":46},{"cluster_no":-1,"count":140},{"cluster_no":1,"count":357}]},{"dimension":15,"min_samples":"13","min_cluster_size":"5","epsilon":"0.0","total_clusters":4,"outliers":146,"Silhouette_score":-0.1460390927,"cluster_results":[{"cluster_no":0,"count":40},{"cluster_no":2,"count":46},{"cluster_no":-1,"count":146},{"cluster_no":1,"count":352}]},{"dimension":15,"min_samples":"13","min_cluster_size":"6","epsilon":"0.0","total_clusters":4,"outliers":146,"Silhouette_score":-0.1460390927,"cluster_results":[{"cluster_no":0,"count":40},{"cluster_no":2,"count":46},{"cluster_no":-1,"count":146},{"cluster_no":1,"count":352}]},{"dimension":15,"min_samples":"13","min_cluster_size":"7","epsilon":"0.0","total_clusters":4,"outliers":146,"Silhouette_score":-0.1460390927,"cluster_results":[{"cluster_no":0,"count":40},{"cluster_no":2,"count":46},{"cluster_no":-1,"count":146},{"cluster_no":1,"count":352}]},{"dimension":15,"min_samples":"13","min_cluster_size":"8","epsilon":"0.0","total_clusters":4,"outliers":146,"Silhouette_score":-0.1460390927,"cluster_results":[{"cluster_no":0,"count":40},{"cluster_no":2,"count":46},{"cluster_no":-1,"count":146},{"cluster_no":1,"count":352}]},{"dimension":15,"min_samples":"13","min_cluster_size":"9","epsilon":"0.0","total_clusters":4,"outliers":146,"Silhouette_score":-0.1460390927,"cluster_results":[{"cluster_no":0,"count":40},{"cluster_no":2,"count":46},{"cluster_no":-1,"count":146},{"cluster_no":1,"count":352}]},{"dimension":15,"min_samples":"13","min_cluster_size":"10","epsilon":"0.0","total_clusters":4,"outliers":146,"Silhouette_score":-0.1460390927,"cluster_results":[{"cluster_no":0,"count":40},{"cluster_no":2,"count":46},{"cluster_no":-1,"count":146},{"cluster_no":1,"count":352}]},{"dimension":15,"min_samples":"13","min_cluster_size":"11","epsilon":"0.0","total_clusters":4,"outliers":146,"Silhouette_score":-0.1460390927,"cluster_results":[{"cluster_no":0,"count":40},{"cluster_no":2,"count":46},{"cluster_no":-1,"count":146},{"cluster_no":1,"count":352}]},{"dimension":15,"min_samples":"13","min_cluster_size":"12","epsilon":"0.0","total_clusters":4,"outliers":146,"Silhouette_score":-0.1460390927,"cluster_results":[{"cluster_no":0,"count":40},{"cluster_no":2,"count":46},{"cluster_no":-1,"count":146},{"cluster_no":1,"count":352}]},{"dimension":15,"min_samples":"13","min_cluster_size":"13","epsilon":"0.0","total_clusters":4,"outliers":146,"Silhouette_score":-0.1460390927,"cluster_results":[{"cluster_no":0,"count":40},{"cluster_no":2,"count":46},{"cluster_no":-1,"count":146},{"cluster_no":1,"count":352}]},{"dimension":15,"min_samples":"13","min_cluster_size":"14","epsilon":"0.0","total_clusters":4,"outliers":146,"Silhouette_score":-0.1460390927,"cluster_results":[{"cluster_no":0,"count":40},{"cluster_no":2,"count":46},{"cluster_no":-1,"count":146},{"cluster_no":1,"count":352}]},{"dimension":15,"min_samples":"13","min_cluster_size":"15","epsilon":"0.0","total_clusters":4,"outliers":146,"Silhouette_score":-0.1460390927,"cluster_results":[{"cluster_no":0,"count":40},{"cluster_no":2,"count":46},{"cluster_no":-1,"count":146},{"cluster_no":1,"count":352}]},{"dimension":15,"min_samples":"14","min_cluster_size":"5","epsilon":"0.0","total_clusters":4,"outliers":159,"Silhouette_score":-0.1516602434,"cluster_results":[{"cluster_no":2,"count":36},{"cluster_no":0,"count":44},{"cluster_no":-1,"count":159},{"cluster_no":1,"count":345}]},{"dimension":15,"min_samples":"14","min_cluster_size":"6","epsilon":"0.0","total_clusters":4,"outliers":159,"Silhouette_score":-0.1516602434,"cluster_results":[{"cluster_no":2,"count":36},{"cluster_no":0,"count":44},{"cluster_no":-1,"count":159},{"cluster_no":1,"count":345}]},{"dimension":15,"min_samples":"14","min_cluster_size":"7","epsilon":"0.0","total_clusters":4,"outliers":159,"Silhouette_score":-0.1516602434,"cluster_results":[{"cluster_no":2,"count":36},{"cluster_no":0,"count":44},{"cluster_no":-1,"count":159},{"cluster_no":1,"count":345}]},{"dimension":15,"min_samples":"14","min_cluster_size":"8","epsilon":"0.0","total_clusters":4,"outliers":159,"Silhouette_score":-0.1516602434,"cluster_results":[{"cluster_no":2,"count":36},{"cluster_no":0,"count":44},{"cluster_no":-1,"count":159},{"cluster_no":1,"count":345}]},{"dimension":15,"min_samples":"14","min_cluster_size":"9","epsilon":"0.0","total_clusters":4,"outliers":159,"Silhouette_score":-0.1516602434,"cluster_results":[{"cluster_no":2,"count":36},{"cluster_no":0,"count":44},{"cluster_no":-1,"count":159},{"cluster_no":1,"count":345}]},{"dimension":15,"min_samples":"14","min_cluster_size":"10","epsilon":"0.0","total_clusters":4,"outliers":159,"Silhouette_score":-0.1516602434,"cluster_results":[{"cluster_no":2,"count":36},{"cluster_no":0,"count":44},{"cluster_no":-1,"count":159},{"cluster_no":1,"count":345}]},{"dimension":15,"min_samples":"14","min_cluster_size":"11","epsilon":"0.0","total_clusters":4,"outliers":159,"Silhouette_score":-0.1516602434,"cluster_results":[{"cluster_no":2,"count":36},{"cluster_no":0,"count":44},{"cluster_no":-1,"count":159},{"cluster_no":1,"count":345}]},{"dimension":15,"min_samples":"14","min_cluster_size":"12","epsilon":"0.0","total_clusters":4,"outliers":159,"Silhouette_score":-0.1516602434,"cluster_results":[{"cluster_no":2,"count":36},{"cluster_no":0,"count":44},{"cluster_no":-1,"count":159},{"cluster_no":1,"count":345}]},{"dimension":15,"min_samples":"14","min_cluster_size":"13","epsilon":"0.0","total_clusters":4,"outliers":159,"Silhouette_score":-0.1516602434,"cluster_results":[{"cluster_no":2,"count":36},{"cluster_no":0,"count":44},{"cluster_no":-1,"count":159},{"cluster_no":1,"count":345}]},{"dimension":15,"min_samples":"14","min_cluster_size":"14","epsilon":"0.0","total_clusters":4,"outliers":159,"Silhouette_score":-0.1516602434,"cluster_results":[{"cluster_no":2,"count":36},{"cluster_no":0,"count":44},{"cluster_no":-1,"count":159},{"cluster_no":1,"count":345}]},{"dimension":15,"min_samples":"14","min_cluster_size":"15","epsilon":"0.0","total_clusters":4,"outliers":159,"Silhouette_score":-0.1516602434,"cluster_results":[{"cluster_no":2,"count":36},{"cluster_no":0,"count":44},{"cluster_no":-1,"count":159},{"cluster_no":1,"count":345}]},{"dimension":15,"min_samples":"15","min_cluster_size":"5","epsilon":"0.0","total_clusters":7,"outliers":264,"Silhouette_score":0.6709183325,"cluster_results":[{"cluster_no":3,"count":19},{"cluster_no":5,"count":22},{"cluster_no":1,"count":34},{"cluster_no":0,"count":44},{"cluster_no":4,"count":44},{"cluster_no":2,"count":157},{"cluster_no":-1,"count":264}]},{"dimension":15,"min_samples":"15","min_cluster_size":"6","epsilon":"0.0","total_clusters":7,"outliers":264,"Silhouette_score":0.6709183325,"cluster_results":[{"cluster_no":3,"count":19},{"cluster_no":5,"count":22},{"cluster_no":1,"count":34},{"cluster_no":0,"count":44},{"cluster_no":4,"count":44},{"cluster_no":2,"count":157},{"cluster_no":-1,"count":264}]},{"dimension":15,"min_samples":"15","min_cluster_size":"7","epsilon":"0.0","total_clusters":7,"outliers":264,"Silhouette_score":0.6709183325,"cluster_results":[{"cluster_no":3,"count":19},{"cluster_no":5,"count":22},{"cluster_no":1,"count":34},{"cluster_no":0,"count":44},{"cluster_no":4,"count":44},{"cluster_no":2,"count":157},{"cluster_no":-1,"count":264}]},{"dimension":15,"min_samples":"15","min_cluster_size":"8","epsilon":"0.0","total_clusters":7,"outliers":264,"Silhouette_score":0.6709183325,"cluster_results":[{"cluster_no":3,"count":19},{"cluster_no":5,"count":22},{"cluster_no":1,"count":34},{"cluster_no":0,"count":44},{"cluster_no":4,"count":44},{"cluster_no":2,"count":157},{"cluster_no":-1,"count":264}]},{"dimension":15,"min_samples":"15","min_cluster_size":"9","epsilon":"0.0","total_clusters":6,"outliers":238,"Silhouette_score":0.6307143101,"cluster_results":[{"cluster_no":4,"count":19},{"cluster_no":1,"count":34},{"cluster_no":0,"count":44},{"cluster_no":3,"count":92},{"cluster_no":2,"count":157},{"cluster_no":-1,"count":238}]},{"dimension":15,"min_samples":"15","min_cluster_size":"10","epsilon":"0.0","total_clusters":6,"outliers":238,"Silhouette_score":0.6307143101,"cluster_results":[{"cluster_no":4,"count":19},{"cluster_no":1,"count":34},{"cluster_no":0,"count":44},{"cluster_no":3,"count":92},{"cluster_no":2,"count":157},{"cluster_no":-1,"count":238}]},{"dimension":15,"min_samples":"15","min_cluster_size":"11","epsilon":"0.0","total_clusters":6,"outliers":238,"Silhouette_score":0.6307143101,"cluster_results":[{"cluster_no":4,"count":19},{"cluster_no":1,"count":34},{"cluster_no":0,"count":44},{"cluster_no":3,"count":92},{"cluster_no":2,"count":157},{"cluster_no":-1,"count":238}]},{"dimension":15,"min_samples":"15","min_cluster_size":"12","epsilon":"0.0","total_clusters":6,"outliers":238,"Silhouette_score":0.6307143101,"cluster_results":[{"cluster_no":4,"count":19},{"cluster_no":1,"count":34},{"cluster_no":0,"count":44},{"cluster_no":3,"count":92},{"cluster_no":2,"count":157},{"cluster_no":-1,"count":238}]},{"dimension":15,"min_samples":"15","min_cluster_size":"13","epsilon":"0.0","total_clusters":6,"outliers":238,"Silhouette_score":0.6307143101,"cluster_results":[{"cluster_no":4,"count":19},{"cluster_no":1,"count":34},{"cluster_no":0,"count":44},{"cluster_no":3,"count":92},{"cluster_no":2,"count":157},{"cluster_no":-1,"count":238}]},{"dimension":15,"min_samples":"15","min_cluster_size":"14","epsilon":"0.0","total_clusters":6,"outliers":238,"Silhouette_score":0.6307143101,"cluster_results":[{"cluster_no":4,"count":19},{"cluster_no":1,"count":34},{"cluster_no":0,"count":44},{"cluster_no":3,"count":92},{"cluster_no":2,"count":157},{"cluster_no":-1,"count":238}]},{"dimension":15,"min_samples":"15","min_cluster_size":"15","epsilon":"0.0","total_clusters":6,"outliers":238,"Silhouette_score":0.6307143101,"cluster_results":[{"cluster_no":4,"count":19},{"cluster_no":1,"count":34},{"cluster_no":0,"count":44},{"cluster_no":3,"count":92},{"cluster_no":2,"count":157},{"cluster_no":-1,"count":238}]}]