[{"No":1,"DocId":18,"key-phrases":["suburb","suburb shape","suburban definition","area","semantics"]},{"No":2,"DocId":20,"key-phrases":["alternative culture","cultural economy","heritage","city","marginal community"]},{"No":3,"DocId":43,"key-phrases":["Transcultural city","transcultural placemaking","urban place","urban space","diverse urban environment"]},{"No":4,"DocId":86,"key-phrases":["Urban planning","metropolitan spatial apartheid","spatial apartheid","cultural identity","place identity"]},{"No":5,"DocId":94,"key-phrases":["art activism","creative city","local cultural policy","occupied theatre","urban governance"]},{"No":6,"DocId":98,"key-phrases":["British suburban literature","suburban literature","suburban identity","contemporary British literature","British literature"]},{"No":7,"DocId":108,"key-phrases":["multilocal creative knowledge","national embeddedness","geographical mobility","transnational multilocality","multilocality"]},{"No":8,"DocId":113,"key-phrases":["cultural policy","new metropolitan age","urban study","cultural policy play","cultural dynamic"]},{"No":9,"DocId":123,"key-phrases":["urban wellbeing","community dance","nurturing urban wellbeing","Vancouver urban governance","City festival"]},{"No":10,"DocId":131,"key-phrases":["urban capitalism","urban economy","Diverse urban theory","urban life","market city"]},{"No":11,"DocId":133,"key-phrases":["urban history","contemporary urban case","urban design","city past","urban built environment"]},{"No":12,"DocId":156,"key-phrases":["cultural expression","globalization","urban public space","urban setting","Visual approach"]},{"No":13,"DocId":157,"key-phrases":["refugee integration","refugee interact","refugee experience","Urban architecture","refugee crisis"]},{"No":14,"DocId":166,"key-phrases":["urban landscape","particular urban landscape","Ponte City project","photographer portrays place","City project"]},{"No":15,"DocId":175,"key-phrases":["modern capital city","modern capital","subnational identity","nationalistic position","nationalism"]},{"No":16,"DocId":190,"key-phrases":["Ethnic tourism","ethnic quarter","tourist community","Many ethnic quarter","urban tourism"]},{"No":17,"DocId":191,"key-phrases":["touristic poverty","tourist commodity","tourism","tourism study","favela"]},{"No":18,"DocId":213,"key-phrases":["ethnic community","immigrant community","intangible cultural history","ethnic community formation","interactive cultural history"]},{"No":19,"DocId":218,"key-phrases":["subway system","City subway system","city subway","York city subway","Underground movement"]},{"No":20,"DocId":231,"key-phrases":["towards urbanity","understand urbanity","urbanity","shift towards urbanity","urbanity serf"]},{"No":21,"DocId":245,"key-phrases":["urban regeneration","capitalist development","urban strategy","trash appear","cultural activity"]},{"No":22,"DocId":280,"key-phrases":["urban modernism","new urban modernism","modern youth identity","modern youth","modern town"]},{"No":23,"DocId":286,"key-phrases":["recent pedestrianization","pedestrianization","cosmopolitanism","urban renewal","urban revitalization"]},{"No":24,"DocId":315,"key-phrases":["Belfast dwells","Irish oral culture","outwith Troubled narrative","Troubled narrative","everyday story"]},{"No":25,"DocId":321,"key-phrases":["urban spectacle","festival","urban semantics","urban environment","spectacle"]},{"No":26,"DocId":327,"key-phrases":["contemporary globalization","global study","socioscapes","international relation","ethnic identity"]},{"No":27,"DocId":337,"key-phrases":["urban planning occur","city building","marginalized periphery","capital","different city"]},{"No":28,"DocId":368,"key-phrases":["global downtowns","heterogeneous downtown today","global downtown","downtown lifestyle","urban anthropology"]}]